{
  "trend": [
    {
      "day": 1,
      "long_fs": {
        "AAPL": 909090.0,
        "AMGN": 909090.0,
        "AXP": 909090.0,
        "CAT": 909090.0,
        "GS": 909090.0,
        "IBM": 909090.0,
        "KO": 909090.0,
        "MCD": 909090.0,
        "MMM": 909090.0,
        "MRK": 909090.0,
        "TRV": 909090.0
      },
      "long_total": 10000000.0,
      "short_fs": {
        "BA": 1250000.0,
        "CRM": 1250000.0,
        "CSCO": 1250000.0,
        "DD": 1250000.0,
        "JNJ": 1250000.0,
        "PG": 1250000.0,
        "VZ": 1250000.0,
        "WBA": 1250000.0
      },
      "short_total": 10000000.0,
      "qutrit_total": 10000000.0,
      "total_cap": 10000000.0,
      "stock_caps": {
        "AAPL": 909090.0,
        "AMGN": 909090.0,
        "AXP": 909090.0,
        "CAT": 909090.0,
        "GS": 909090.0,
        "IBM": 909090.0,
        "KO": 909090.0,
        "MCD": 909090.0,
        "MMM": 909090.0,
        "MRK": 909090.0,
        "TRV": 909090.0,
        "BA": 1250000.0,
        "CRM": 1250000.0,
        "CSCO": 1250000.0,
        "DD": 1250000.0,
        "JNJ": 1250000.0,
        "PG": 1250000.0,
        "VZ": 1250000.0,
        "WBA": 1250000.0
      }
    },
    {
      "day": 2,
      "long_fs": {
        "AAPL": 927805.2000000002,
        "AMGN": 922731.6799999999,
        "AXP": 920576.25,
        "CAT": 957716.16,
        "GS": 931740.42,
        "IBM": 927933.5,
        "KO": 915782.28,
        "MCD": 914058.8300000001,
        "MMM": 924562.66,
        "MRK": 912952.8,
        "TRV": 940833.6200000001
      },
      "long_total": 10196703.400000002,
      "short_fs": {
        "BA": 1231402.3,
        "CRM": 1241045.0999999999,
        "CSCO": 1214985.95,
        "DD": 1225535.6,
        "JNJ": 1234453.1600000001,
        "PG": 1246070.1500000001,
        "VZ": 1237758.76,
        "WBA": 1218341.06
      },
      "short_total": 9849592.08,
      "qutrit_total": 10046295.480000004,
      "total_cap": 10046295.480000004,
      "stock_caps": {
        "AAPL": 927805.2000000002,
        "AMGN": 922731.6799999999,
        "AXP": 920576.25,
        "CAT": 957716.16,
        "GS": 931740.42,
        "IBM": 927933.5,
        "KO": 915782.28,
        "MCD": 914058.8300000001,
        "MMM": 924562.66,
        "MRK": 912952.8,
        "TRV": 940833.6200000001,
        "BA": 1231402.3,
        "CRM": 1241045.0999999999,
        "CSCO": 1214985.95,
        "DD": 1225535.6,
        "JNJ": 1234453.1600000001,
        "PG": 1246070.1500000001,
        "VZ": 1237758.76,
        "WBA": 1218341.06
      }
    },
    {
      "day": 3,
      "long_fs": {
        "AAPL": 925967.1000000001,
        "AMGN": 939077.4799999999,
        "AXP": 918432.1499999999,
        "CAT": 968853.44,
        "GS": 923544.1800000002,
        "IBM": 943397.0,
        "KO": 916419.64,
        "MCD": 897786.8600000001,
        "MMM": 931397.67,
        "MRK": 918747.0,
        "TRV": 940400.26
      },
      "long_total": 10224032.78,
      "short_fs": {
        "BA": 1288862.78,
        "CRM": 1274761.2,
        "CSCO": 1216816.75,
        "DD": 1229006.9000000001,
        "JNJ": 1215857.9200000002,
        "PG": 1241441.6600000001,
        "VZ": 1225517.52,
        "WBA": 1202511.59
      },
      "short_total": 9894776.32,
      "qutrit_total": 10118809.100000001,
      "total_cap": 10118809.100000001,
      "stock_caps": {
        "AAPL": 925967.1000000001,
        "AMGN": 939077.4799999999,
        "AXP": 918432.1499999999,
        "CAT": 968853.44,
        "GS": 923544.1800000002,
        "IBM": 943397.0,
        "KO": 916419.64,
        "MCD": 897786.8600000001,
        "MMM": 931397.67,
        "MRK": 918747.0,
        "TRV": 940400.26,
        "BA": 1288862.78,
        "CRM": 1274761.2,
        "CSCO": 1216816.75,
        "DD": 1229006.9000000001,
        "JNJ": 1215857.9200000002,
        "PG": 1241441.6600000001,
        "VZ": 1225517.52,
        "WBA": 1202511.59
      }
    },
    {
      "day": 4,
      "long_fs": {
        "AAPL": 908922.9,
        "AMGN": 940167.2,
        "AXP": 883003.45,
        "CAT": 972880.76,
        "GS": 913160.4300000002,
        "IBM": 948636.0,
        "KO": 917853.7000000001,
        "MCD": 894600.74,
        "MMM": 921483.1500000001,
        "MRK": 926858.8800000001,
        "TRV": 939316.8600000001
      },
      "long_total": 10166894.07,
      "short_fs": {
        "BA": 1340230.91,
        "CRM": 1285218.5999999999,
        "CSCO": 1206747.35,
        "DD": 1270331.9000000001,
        "JNJ": 1208236.9200000002,
        "PG": 1235066.5699999998,
        "VZ": 1215223.75,
        "WBA": 1174740.59
      },
      "short_total": 9935796.59,
      "qutrit_total": 10102690.66,
      "total_cap": 10102690.66,
      "stock_caps": {
        "AAPL": 908922.9,
        "AMGN": 940167.2,
        "AXP": 883003.45,
        "CAT": 972880.76,
        "GS": 913160.4300000002,
        "IBM": 948636.0,
        "KO": 917853.7000000001,
        "MCD": 894600.74,
        "MMM": 921483.1500000001,
        "MRK": 926858.8800000001,
        "TRV": 939316.8600000001,
        "BA": 1340230.91,
        "CRM": 1285218.5999999999,
        "CSCO": 1206747.35,
        "DD": 1270331.9000000001,
        "JNJ": 1208236.9200000002,
        "PG": 1235066.5699999998,
        "VZ": 1215223.75,
        "WBA": 1174740.59
      }
    },
    {
      "day": 5,
      "long_fs": {
        "AAPL": 887367.0000000002,
        "AMGN": 946019.4,
        "AXP": 812452.35,
        "CAT": 978051.6399999999,
        "GS": 891617.61,
        "IBM": 944495.5,
        "KO": 896024.12,
        "MCD": 851057.1000000001,
        "MMM": 899851.47,
        "MRK": 925571.2799999999,
        "TRV": 919761.49
      },
      "long_total": 9952278.96,
      "short_fs": {
        "BA": 1415070.62,
        "CRM": 1325786.0999999999,
        "CSCO": 1227801.5499999998,
        "DD": 1358271.5000000002,
        "JNJ": 1187431.5899999999,
        "PG": 1253842.52,
        "VZ": 1225239.31,
        "WBA": 1195013.42
      },
      "short_total": 10188456.61,
      "qutrit_total": 10140735.57,
      "total_cap": 10140735.57,
      "stock_caps": {
        "AAPL": 887367.0000000002,
        "AMGN": 946019.4,
        "AXP": 812452.35,
        "CAT": 978051.6399999999,
        "GS": 891617.61,
        "IBM": 944495.5,
        "KO": 896024.12,
        "MCD": 851057.1000000001,
        "MMM": 899851.47,
        "MRK": 925571.2799999999,
        "TRV": 919761.49,
        "BA": 1415070.62,
        "CRM": 1325786.0999999999,
        "CSCO": 1227801.5499999998,
        "DD": 1358271.5000000002,
        "JNJ": 1187431.5899999999,
        "PG": 1253842.52,
        "VZ": 1225239.31,
        "WBA": 1195013.42
      }
    },
    {
      "day": 6,
      "long_fs": {
        "AAPL": 877006.8,
        "AMGN": 932862.0399999999,
        "AXP": 817148.95,
        "CAT": 1044179.24,
        "GS": 890177.7300000001,
        "IBM": 941538.0,
        "KO": 860491.3,
        "MCD": 845215.88,
        "MMM": 913145.94,
        "MRK": 916300.5599999999,
        "TRV": 912502.71
      },
      "long_total": 9950579.150000002,
      "short_fs": {
        "BA": 1385378.43,
        "CRM": 1350607.4000000001,
        "CSCO": 1255034.7,
        "DD": 1362569.3,
        "JNJ": 1214028.8800000001,
        "PG": 1303183.97,
        "VZ": 1258624.51,
        "WBA": 1181683.34
      },
      "short_total": 10311110.53,
      "qutrit_total": 10261689.68,
      "total_cap": 10261689.68,
      "stock_caps": {
        "AAPL": 877006.8,
        "AMGN": 932862.0399999999,
        "AXP": 817148.95,
        "CAT": 1044179.24,
        "GS": 890177.7300000001,
        "IBM": 941538.0,
        "KO": 860491.3,
        "MCD": 845215.88,
        "MMM": 913145.94,
        "MRK": 916300.5599999999,
        "TRV": 912502.71,
        "BA": 1385378.43,
        "CRM": 1350607.4000000001,
        "CSCO": 1255034.7,
        "DD": 1362569.3,
        "JNJ": 1214028.8800000001,
        "PG": 1303183.97,
        "VZ": 1258624.51,
        "WBA": 1181683.34
      }
    },
    {
      "day": 7,
      "long_fs": {
        "AAPL": 907697.5,
        "AMGN": 934315.0,
        "AXP": 861051.95,
        "CAT": 1043085.4,
        "GS": 924014.91,
        "IBM": 945594.0,
        "KO": 864952.8200000001,
        "MCD": 844002.12,
        "MMM": 920732.05,
        "MRK": 926343.84,
        "TRV": 928320.3500000001
      },
      "long_total": 10100119.94,
      "short_fs": {
        "BA": 1354852.55,
        "CRM": 1284317.1,
        "CSCO": 1220249.5,
        "DD": 1301738.9000000001,
        "JNJ": 1209151.44,
        "PG": 1287027.9200000002,
        "VZ": 1262519.4500000002,
        "WBA": 1163632.19
      },
      "short_total": 10083489.049999999,
      "qutrit_total": 10183608.989999998,
      "total_cap": 10183608.989999998,
      "stock_caps": {
        "AAPL": 907697.5,
        "AMGN": 934315.0,
        "AXP": 861051.95,
        "CAT": 1043085.4,
        "GS": 924014.91,
        "IBM": 945594.0,
        "KO": 864952.8200000001,
        "MCD": 844002.12,
        "MMM": 920732.05,
        "MRK": 926343.84,
        "TRV": 928320.3500000001,
        "BA": 1354852.55,
        "CRM": 1284317.1,
        "CSCO": 1220249.5,
        "DD": 1301738.9000000001,
        "JNJ": 1209151.44,
        "PG": 1287027.9200000002,
        "VZ": 1262519.4500000002,
        "WBA": 1163632.19
      }
    },
    {
      "day": 8,
      "long_fs": {
        "AAPL": 883022.4000000001,
        "AMGN": 916112.6399999999,
        "AXP": 865901.7,
        "CAT": 1053079.1199999999,
        "GS": 913797.3,
        "IBM": 931567.0,
        "KO": 849018.8200000001,
        "MCD": 842219.41,
        "MMM": 903907.41,
        "MRK": 927502.68,
        "TRV": 931137.19
      },
      "long_total": 10017275.67,
      "short_fs": {
        "BA": 1355942.76,
        "CRM": 1302287.0,
        "CSCO": 1247940.3499999999,
        "DD": 1308516.2000000002,
        "JNJ": 1206865.1400000001,
        "PG": 1318292.06,
        "VZ": 1258902.72,
        "WBA": 1165020.74
      },
      "short_total": 10163766.97,
      "qutrit_total": 10181042.64,
      "total_cap": 10181042.64,
      "stock_caps": {
        "AAPL": 883022.4000000001,
        "AMGN": 916112.6399999999,
        "AXP": 865901.7,
        "CAT": 1053079.1199999999,
        "GS": 913797.3,
        "IBM": 931567.0,
        "KO": 849018.8200000001,
        "MCD": 842219.41,
        "MMM": 903907.41,
        "MRK": 927502.68,
        "TRV": 931137.19,
        "BA": 1355942.76,
        "CRM": 1302287.0,
        "CSCO": 1247940.3499999999,
        "DD": 1308516.2000000002,
        "JNJ": 1206865.1400000001,
        "PG": 1318292.06,
        "VZ": 1258902.72,
        "WBA": 1165020.74
      }
    },
    {
      "day": 9,
      "long_fs": {
        "AAPL": 861912.1000000001,
        "AMGN": 923781.0399999999,
        "AXP": 857223.2,
        "CAT": 1068194.0,
        "GS": 905767.2000000001,
        "IBM": 928694.0,
        "KO": 849656.18,
        "MCD": 860691.3200000001,
        "MMM": 885280.13,
        "MRK": 931880.5200000001,
        "TRV": 941104.47
      },
      "long_total": 10014194.16,
      "short_fs": {
        "BA": 1369794.84,
        "CRM": 1315749.4,
        "CSCO": 1248398.05,
        "DD": 1301738.9000000001,
        "JNJ": 1209227.6500000001,
        "PG": 1332264.86,
        "VZ": 1263354.0799999998,
        "WBA": 1182516.47
      },
      "short_total": 10223044.250000002,
      "qutrit_total": 10237238.410000004,
      "total_cap": 10237238.410000004,
      "stock_caps": {
        "AAPL": 861912.1000000001,
        "AMGN": 923781.0399999999,
        "AXP": 857223.2,
        "CAT": 1068194.0,
        "GS": 905767.2000000001,
        "IBM": 928694.0,
        "KO": 849656.18,
        "MCD": 860691.3200000001,
        "MMM": 885280.13,
        "MRK": 931880.5200000001,
        "TRV": 941104.47,
        "BA": 1369794.84,
        "CRM": 1315749.4,
        "CSCO": 1248398.05,
        "DD": 1301738.9000000001,
        "JNJ": 1209227.6500000001,
        "PG": 1332264.86,
        "VZ": 1263354.0799999998,
        "WBA": 1182516.47
      }
    },
    {
      "day": 10,
      "long_fs": {
        "AAPL": 839019.4000000001,
        "AMGN": 925234.0,
        "AXP": 882186.6499999999,
        "CAT": 1071226.92,
        "GS": 900173.8200000001,
        "IBM": 928525.0,
        "KO": 865271.5,
        "MCD": 858074.15,
        "MMM": 901128.3400000001,
        "MRK": 934455.72,
        "TRV": 959793.1200000001
      },
      "long_total": 10065098.620000001,
      "short_fs": {
        "BA": 1374348.0699999998,
        "CRM": 1344357.0,
        "CSCO": 1257323.2,
        "DD": 1314136.4000000001,
        "JNJ": 1191394.51,
        "PG": 1317331.4300000002,
        "VZ": 1275873.53,
        "WBA": 1169464.1
      },
      "short_total": 10244228.239999998,
      "qutrit_total": 10309326.86,
      "total_cap": 10309326.86,
      "stock_caps": {
        "AAPL": 839019.4000000001,
        "AMGN": 925234.0,
        "AXP": 882186.6499999999,
        "CAT": 1071226.92,
        "GS": 900173.8200000001,
        "IBM": 928525.0,
        "KO": 865271.5,
        "MCD": 858074.15,
        "MMM": 901128.3400000001,
        "MRK": 934455.72,
        "TRV": 959793.1200000001,
        "BA": 1374348.0699999998,
        "CRM": 1344357.0,
        "CSCO": 1257323.2,
        "DD": 1314136.4000000001,
        "JNJ": 1191394.51,
        "PG": 1317331.4300000002,
        "VZ": 1275873.53,
        "WBA": 1169464.1
      }
    },
    {
      "day": 11,
      "long_fs": {
        "AAPL": 863917.3000000002,
        "AMGN": 934718.6,
        "AXP": 898777.8999999999,
        "CAT": 1076298.36,
        "GS": 911748.2400000001,
        "IBM": 941284.5,
        "KO": 881364.8400000001,
        "MCD": 882311.42,
        "MMM": 906310.93,
        "MRK": 944756.5200000001,
        "TRV": 976098.29
      },
      "long_total": 10217596.899999999,
      "short_fs": {
        "BA": 1346323.26,
        "CRM": 1326327.0,
        "CSCO": 1227572.7,
        "DD": 1311987.5,
        "JNJ": 1157481.06,
        "PG": 1274801.72,
        "VZ": 1270031.1199999999,
        "WBA": 1162243.64
      },
      "short_total": 10076768.0,
      "qutrit_total": 10294364.899999999,
      "total_cap": 10294364.899999999,
      "stock_caps": {
        "AAPL": 863917.3000000002,
        "AMGN": 934718.6,
        "AXP": 898777.8999999999,
        "CAT": 1076298.36,
        "GS": 911748.2400000001,
        "IBM": 941284.5,
        "KO": 881364.8400000001,
        "MCD": 882311.42,
        "MMM": 906310.93,
        "MRK": 944756.5200000001,
        "TRV": 976098.29,
        "BA": 1346323.26,
        "CRM": 1326327.0,
        "CSCO": 1227572.7,
        "DD": 1311987.5,
        "JNJ": 1157481.06,
        "PG": 1274801.72,
        "VZ": 1270031.1199999999,
        "WBA": 1162243.64
      }
    },
    {
      "day": 12,
      "long_fs": {
        "AAPL": 888982.3000000002,
        "AMGN": 935162.5599999999,
        "AXP": 922107.75,
        "CAT": 1074409.0,
        "GS": 943868.64,
        "IBM": 951762.5,
        "KO": 878974.74,
        "MCD": 903438.4299999999,
        "MMM": 913821.93,
        "MRK": 938576.04,
        "TRV": 971222.99
      },
      "long_total": 10322336.88,
      "short_fs": {
        "BA": 1287964.96,
        "CRM": 1269893.1,
        "CSCO": 1222766.8499999999,
        "DD": 1272811.4000000001,
        "JNJ": 1169827.0799999998,
        "PG": 1278993.56,
        "VZ": 1276151.74,
        "WBA": 1184182.73
      },
      "short_total": 9962591.420000002,
      "qutrit_total": 10284928.300000004,
      "total_cap": 10284928.300000004,
      "stock_caps": {
        "AAPL": 888982.3000000002,
        "AMGN": 935162.5599999999,
        "AXP": 922107.75,
        "CAT": 1074409.0,
        "GS": 943868.64,
        "IBM": 951762.5,
        "KO": 878974.74,
        "MCD": 903438.4299999999,
        "MMM": 913821.93,
        "MRK": 938576.04,
        "TRV": 971222.99,
        "BA": 1287964.96,
        "CRM": 1269893.1,
        "CSCO": 1222766.8499999999,
        "DD": 1272811.4000000001,
        "JNJ": 1169827.0799999998,
        "PG": 1278993.56,
        "VZ": 1276151.74,
        "WBA": 1184182.73
      }
    },
    {
      "day": 13,
      "long_fs": {
        "AAPL": 894719.4000000001,
        "AMGN": 952073.4,
        "AXP": 954575.5499999999,
        "CAT": 1102351.64,
        "GS": 950818.8300000001,
        "IBM": 958607.0,
        "KO": 888216.4600000001,
        "MCD": 900897.12,
        "MMM": 927567.06,
        "MRK": 948361.8,
        "TRV": 980648.5700000001
      },
      "long_total": 10458846.830000002,
      "short_fs": {
        "BA": 1280269.36,
        "CRM": 1240924.9000000001,
        "CSCO": 1214528.25,
        "DD": 1246859.3,
        "JNJ": 1152451.2,
        "PG": 1275151.04,
        "VZ": 1279212.0499999998,
        "WBA": 1181405.6300000001
      },
      "short_total": 9870801.730000002,
      "qutrit_total": 10329648.560000002,
      "total_cap": 10329648.560000002,
      "stock_caps": {
        "AAPL": 894719.4000000001,
        "AMGN": 952073.4,
        "AXP": 954575.5499999999,
        "CAT": 1102351.64,
        "GS": 950818.8300000001,
        "IBM": 958607.0,
        "KO": 888216.4600000001,
        "MCD": 900897.12,
        "MMM": 927567.06,
        "MRK": 948361.8,
        "TRV": 980648.5700000001,
        "BA": 1280269.36,
        "CRM": 1240924.9000000001,
        "CSCO": 1214528.25,
        "DD": 1246859.3,
        "JNJ": 1152451.2,
        "PG": 1275151.04,
        "VZ": 1279212.0499999998,
        "WBA": 1181405.6300000001
      }
    },
    {
      "day": 14,
      "long_fs": {
        "AAPL": 913434.6000000001,
        "AMGN": 953647.44,
        "AXP": 973719.2999999999,
        "CAT": 1098423.76,
        "GS": 956661.42,
        "IBM": 964606.5,
        "KO": 888375.8,
        "MCD": 906396.97,
        "MMM": 931472.78,
        "MRK": 950421.9600000001,
        "TRV": 976748.3300000001
      },
      "long_total": 10513918.86,
      "short_fs": {
        "BA": 1263339.0399999998,
        "CRM": 1190741.4,
        "CSCO": 1219105.25,
        "DD": 1231982.3000000003,
        "JNJ": 1167388.3599999999,
        "PG": 1275762.35,
        "VZ": 1315657.56,
        "WBA": 1184738.15
      },
      "short_total": 9848714.41,
      "qutrit_total": 10362633.27,
      "total_cap": 10362633.27,
      "stock_caps": {
        "AAPL": 913434.6000000001,
        "AMGN": 953647.44,
        "AXP": 973719.2999999999,
        "CAT": 1098423.76,
        "GS": 956661.42,
        "IBM": 964606.5,
        "KO": 888375.8,
        "MCD": 906396.97,
        "MMM": 931472.78,
        "MRK": 950421.9600000001,
        "TRV": 976748.3300000001,
        "BA": 1263339.0399999998,
        "CRM": 1190741.4,
        "CSCO": 1219105.25,
        "DD": 1231982.3000000003,
        "JNJ": 1167388.3599999999,
        "PG": 1275762.35,
        "VZ": 1315657.56,
        "WBA": 1184738.15
      }
    },
    {
      "day": 15,
      "long_fs": {
        "AAPL": 921232.6000000001,
        "AMGN": 953929.96,
        "AXP": 965398.15,
        "CAT": 1112345.36,
        "GS": 938995.2000000001,
        "IBM": 959705.5,
        "KO": 895546.1000000001,
        "MCD": 892742.17,
        "MMM": 933125.2000000001,
        "MRK": 949778.16,
        "TRV": 988828.24
      },
      "long_total": 10511636.64,
      "short_fs": {
        "BA": 1307781.13,
        "CRM": 1221091.9,
        "CSCO": 1218418.7,
        "DD": 1231321.1,
        "JNJ": 1159843.5699999998,
        "PG": 1271133.86,
        "VZ": 1308702.31,
        "WBA": 1184182.73
      },
      "short_total": 9902475.3,
      "qutrit_total": 10414111.940000001,
      "total_cap": 10414111.940000001,
      "stock_caps": {
        "AAPL": 921232.6000000001,
        "AMGN": 953929.96,
        "AXP": 965398.15,
        "CAT": 1112345.36,
        "GS": 938995.2000000001,
        "IBM": 959705.5,
        "KO": 895546.1000000001,
        "MCD": 892742.17,
        "MMM": 933125.2000000001,
        "MRK": 949778.16,
        "TRV": 988828.24,
        "BA": 1307781.13,
        "CRM": 1221091.9,
        "CSCO": 1218418.7,
        "DD": 1231321.1,
        "JNJ": 1159843.5699999998,
        "PG": 1271133.86,
        "VZ": 1308702.31,
        "WBA": 1184182.73
      }
    },
    {
      "day": 16,
      "long_fs": {
        "AAPL": 940393.4,
        "AMGN": 954535.36,
        "AXP": 976833.35,
        "CAT": 1107373.36,
        "GS": 950098.89,
        "IBM": 966888.0,
        "KO": 898732.9,
        "MCD": 903362.5700000001,
        "MMM": 941687.7400000001,
        "MRK": 952739.64,
        "TRV": 989694.96
      },
      "long_total": 10582350.170000002,
      "short_fs": {
        "BA": 1274818.31,
        "CRM": 1194227.2,
        "CSCO": 1214528.25,
        "DD": 1226692.7,
        "JNJ": 1166169.0,
        "PG": 1261702.22,
        "VZ": 1310927.99,
        "WBA": 1182794.18
      },
      "short_total": 9831859.85,
      "qutrit_total": 10414210.020000003,
      "total_cap": 10414210.020000003,
      "stock_caps": {
        "AAPL": 940393.4,
        "AMGN": 954535.36,
        "AXP": 976833.35,
        "CAT": 1107373.36,
        "GS": 950098.89,
        "IBM": 966888.0,
        "KO": 898732.9,
        "MCD": 903362.5700000001,
        "MMM": 941687.7400000001,
        "MRK": 952739.64,
        "TRV": 989694.96,
        "BA": 1274818.31,
        "CRM": 1194227.2,
        "CSCO": 1214528.25,
        "DD": 1226692.7,
        "JNJ": 1166169.0,
        "PG": 1261702.22,
        "VZ": 1310927.99,
        "WBA": 1182794.18
      }
    },
    {
      "day": 17,
      "long_fs": {
        "AAPL": 948135.7000000002,
        "AMGN": 945292.9199999999,
        "AXP": 949725.8,
        "CAT": 1104688.48,
        "GS": 929608.2900000002,
        "IBM": 961142.0,
        "KO": 892837.3200000001,
        "MCD": 895776.5700000001,
        "MMM": 927491.9500000001,
        "MRK": 957890.04,
        "TRV": 983844.6000000001
      },
      "long_total": 10496443.67,
      "short_fs": {
        "BA": 1306883.31,
        "CRM": 1236717.9,
        "CSCO": 1253203.9,
        "DD": 1244710.4000000001,
        "JNJ": 1171198.8599999999,
        "PG": 1270347.8900000001,
        "VZ": 1311762.6199999999,
        "WBA": 1201956.17
      },
      "short_total": 9996781.049999999,
      "qutrit_total": 10493224.719999999,
      "total_cap": 10493224.719999999,
      "stock_caps": {
        "AAPL": 948135.7000000002,
        "AMGN": 945292.9199999999,
        "AXP": 949725.8,
        "CAT": 1104688.48,
        "GS": 929608.2900000002,
        "IBM": 961142.0,
        "KO": 892837.3200000001,
        "MCD": 895776.5700000001,
        "MMM": 927491.9500000001,
        "MRK": 957890.04,
        "TRV": 983844.6000000001,
        "BA": 1306883.31,
        "CRM": 1236717.9,
        "CSCO": 1253203.9,
        "DD": 1244710.4000000001,
        "JNJ": 1171198.8599999999,
        "PG": 1270347.8900000001,
        "VZ": 1311762.6199999999,
        "WBA": 1201956.17
      }
    },
    {
      "day": 18,
      "long_fs": {
        "AAPL": 969635.9,
        "AMGN": 956149.76,
        "AXP": 964377.1499999999,
        "CAT": 1104887.36,
        "GS": 931325.0700000001,
        "IBM": 968324.5,
        "KO": 901441.68,
        "MCD": 911479.59,
        "MMM": 935678.94,
        "MRK": 966001.9199999999,
        "TRV": 997928.8
      },
      "long_total": 10607240.67,
      "short_fs": {
        "BA": 1287580.18,
        "CRM": 1219589.4,
        "CSCO": 1252746.2,
        "DD": 1238759.6,
        "JNJ": 1164339.96,
        "PG": 1268164.6400000001,
        "VZ": 1310927.99,
        "WBA": 1194180.2899999998
      },
      "short_total": 9936288.26,
      "qutrit_total": 10543528.93,
      "total_cap": 10543528.93,
      "stock_caps": {
        "AAPL": 969635.9,
        "AMGN": 956149.76,
        "AXP": 964377.1499999999,
        "CAT": 1104887.36,
        "GS": 931325.0700000001,
        "IBM": 968324.5,
        "KO": 901441.68,
        "MCD": 911479.59,
        "MMM": 935678.94,
        "MRK": 966001.9199999999,
        "TRV": 997928.8,
        "BA": 1287580.18,
        "CRM": 1219589.4,
        "CSCO": 1252746.2,
        "DD": 1238759.6,
        "JNJ": 1164339.96,
        "PG": 1268164.6400000001,
        "VZ": 1310927.99,
        "WBA": 1194180.2899999998
      }
    },
    {
      "day": 19,
      "long_fs": {
        "AAPL": 973256.4000000001,
        "AMGN": 963898.8799999999,
        "AXP": 971473.1,
        "CAT": 1110605.1600000001,
        "GS": 934814.0100000001,
        "IBM": 984041.5,
        "KO": 909568.02,
        "MCD": 916486.3500000001,
        "MMM": 944917.47,
        "MRK": 977204.04,
        "TRV": 1017050.81
      },
      "long_total": 10703325.74,
      "short_fs": {
        "BA": 1288221.48,
        "CRM": 1237198.7,
        "CSCO": 1241990.25,
        "DD": 1225700.9,
        "JNJ": 1151536.6800000002,
        "PG": 1253929.85,
        "VZ": 1304529.16,
        "WBA": 1191403.19
      },
      "short_total": 9894510.209999999,
      "qutrit_total": 10597835.95,
      "total_cap": 10597835.95,
      "stock_caps": {
        "AAPL": 973256.4000000001,
        "AMGN": 963898.8799999999,
        "AXP": 971473.1,
        "CAT": 1110605.1600000001,
        "GS": 934814.0100000001,
        "IBM": 984041.5,
        "KO": 909568.02,
        "MCD": 916486.3500000001,
        "MMM": 944917.47,
        "MRK": 977204.04,
        "TRV": 1017050.81,
        "BA": 1288221.48,
        "CRM": 1237198.7,
        "CSCO": 1241990.25,
        "DD": 1225700.9,
        "JNJ": 1151536.6800000002,
        "PG": 1253929.85,
        "VZ": 1304529.16,
        "WBA": 1191403.19
      }
    },
    {
      "day": 20,
      "long_fs": {
        "AAPL": 978158.0000000001,
        "AMGN": 970679.36,
        "AXP": 968512.2,
        "CAT": 1103097.44,
        "GS": 928749.9000000001,
        "IBM": 984971.0,
        "KO": 915304.26,
        "MCD": 921644.8300000001,
        "MMM": 938683.3400000001,
        "MRK": 975658.9199999999,
        "TRV": 1011687.98
      },
      "long_total": 10697157.23,
      "short_fs": {
        "BA": 1293287.75,
        "CRM": 1211776.4,
        "CSCO": 1238099.7999999998,
        "DD": 1238098.4,
        "JNJ": 1144601.5699999998,
        "PG": 1245371.51,
        "VZ": 1307033.0499999998,
        "WBA": 1189459.22
      },
      "short_total": 9867727.700000001,
      "qutrit_total": 10564884.93,
      "total_cap": 10564884.93,
      "stock_caps": {
        "AAPL": 978158.0000000001,
        "AMGN": 970679.36,
        "AXP": 968512.2,
        "CAT": 1103097.44,
        "GS": 928749.9000000001,
        "IBM": 984971.0,
        "KO": 915304.26,
        "MCD": 921644.8300000001,
        "MMM": 938683.3400000001,
        "MRK": 975658.9199999999,
        "TRV": 1011687.98,
        "BA": 1293287.75,
        "CRM": 1211776.4,
        "CSCO": 1238099.7999999998,
        "DD": 1238098.4,
        "JNJ": 1144601.5699999998,
        "PG": 1245371.51,
        "VZ": 1307033.0499999998,
        "WBA": 1189459.22
      }
    },
    {
      "day": 21,
      "long_fs": {
        "AAPL": 996873.2000000002,
        "AMGN": 974997.8799999999,
        "AXP": 974842.3999999999,
        "CAT": 1099070.1199999999,
        "GS": 940822.7400000001,
        "IBM": 988435.5,
        "KO": 918809.74,
        "MCD": 941482.22,
        "MMM": 955132.43,
        "MRK": 980036.76,
        "TRV": 995707.8300000001
      },
      "long_total": 10766220.82,
      "short_fs": {
        "BA": 1257118.43,
        "CRM": 1175836.6,
        "CSCO": 1225970.75,
        "DD": 1210658.6,
        "JNJ": 1145287.46,
        "PG": 1232534.0,
        "VZ": 1305085.5799999998,
        "WBA": 1171963.49
      },
      "short_total": 9724454.91,
      "qutrit_total": 10490675.73,
      "total_cap": 10490675.73,
      "stock_caps": {
        "AAPL": 996873.2000000002,
        "AMGN": 974997.8799999999,
        "AXP": 974842.3999999999,
        "CAT": 1099070.1199999999,
        "GS": 940822.7400000001,
        "IBM": 988435.5,
        "KO": 918809.74,
        "MCD": 941482.22,
        "MMM": 955132.43,
        "MRK": 980036.76,
        "TRV": 995707.8300000001,
        "BA": 1257118.43,
        "CRM": 1175836.6,
        "CSCO": 1225970.75,
        "DD": 1210658.6,
        "JNJ": 1145287.46,
        "PG": 1232534.0,
        "VZ": 1305085.5799999998,
        "WBA": 1171963.49
      }
    },
    {
      "day": 22,
      "long_fs": {
        "AAPL": 990244.9000000001,
        "AMGN": 979154.96,
        "AXP": 968818.4999999999,
        "CAT": 1109213.0,
        "GS": 929552.91,
        "IBM": 989872.0,
        "KO": 919606.4400000001,
        "MCD": 944744.2000000001,
        "MMM": 951001.38,
        "MRK": 989951.2799999999,
        "TRV": 1005133.4100000001
      },
      "long_total": 10777302.98,
      "short_fs": {
        "BA": 1250000.0,
        "CRM": 1213819.8,
        "CSCO": 1217274.45,
        "DD": 1234792.4,
        "JNJ": 1131188.6099999999,
        "PG": 1241179.6700000002,
        "VZ": 1296739.28,
        "WBA": 1181961.0499999998
      },
      "short_total": 9766955.259999998,
      "qutrit_total": 10544258.239999998,
      "total_cap": 10544258.239999998,
      "stock_caps": {
        "AAPL": 990244.9000000001,
        "AMGN": 979154.96,
        "AXP": 968818.4999999999,
        "CAT": 1109213.0,
        "GS": 929552.91,
        "IBM": 989872.0,
        "KO": 919606.4400000001,
        "MCD": 944744.2000000001,
        "MMM": 951001.38,
        "MRK": 989951.2799999999,
        "TRV": 1005133.4100000001,
        "BA": 1250000.0,
        "CRM": 1213819.8,
        "CSCO": 1217274.45,
        "DD": 1234792.4,
        "JNJ": 1131188.6099999999,
        "PG": 1241179.6700000002,
        "VZ": 1296739.28,
        "WBA": 1181961.0499999998
      }
    },
    {
      "day": 23,
      "long_fs": {
        "AAPL": 972643.7000000002,
        "AMGN": 976127.96,
        "AXP": 954728.7,
        "CAT": 1107920.28,
        "GS": 914351.1000000001,
        "IBM": 974070.5,
        "KO": 916419.64,
        "MCD": 938106.4500000001,
        "MMM": 935002.9500000001,
        "MRK": 985702.2,
        "TRV": 989857.47
      },
      "long_total": 10664940.95,
      "short_fs": {
        "BA": 1271868.33,
        "CRM": 1229505.9,
        "CSCO": 1223911.1,
        "DD": 1283721.2000000002,
        "JNJ": 1149174.1700000002,
        "PG": 1254191.84,
        "VZ": 1312319.04,
        "WBA": 1256665.0399999998
      },
      "short_total": 9981356.62,
      "qutrit_total": 10646297.57,
      "total_cap": 10646297.57,
      "stock_caps": {
        "AAPL": 972643.7000000002,
        "AMGN": 976127.96,
        "AXP": 954728.7,
        "CAT": 1107920.28,
        "GS": 914351.1000000001,
        "IBM": 974070.5,
        "KO": 916419.64,
        "MCD": 938106.4500000001,
        "MMM": 935002.9500000001,
        "MRK": 985702.2,
        "TRV": 989857.47,
        "BA": 1271868.33,
        "CRM": 1229505.9,
        "CSCO": 1223911.1,
        "DD": 1283721.2000000002,
        "JNJ": 1149174.1700000002,
        "PG": 1254191.84,
        "VZ": 1312319.04,
        "WBA": 1256665.0399999998
      }
    },
    {
      "day": 24,
      "long_fs": {
        "AAPL": 970972.7000000002,
        "AMGN": 981374.76,
        "AXP": 955596.5499999999,
        "CAT": 1092755.68,
        "GS": 914683.3800000001,
        "IBM": 975000.0,
        "KO": 929326.18,
        "MCD": 945578.66,
        "MMM": 940110.43,
        "MRK": 1003471.0800000001,
        "TRV": 1003508.31
      },
      "long_total": 10712387.73,
      "short_fs": {
        "BA": 1276613.95,
        "CRM": 1229926.6,
        "CSCO": 1226199.6,
        "DD": 1264381.1,
        "JNJ": 1141858.01,
        "PG": 1235503.22,
        "VZ": 1284776.25,
        "WBA": 1281936.65
      },
      "short_total": 9941195.38,
      "qutrit_total": 10653583.11,
      "total_cap": 10653583.11,
      "stock_caps": {
        "AAPL": 970972.7000000002,
        "AMGN": 981374.76,
        "AXP": 955596.5499999999,
        "CAT": 1092755.68,
        "GS": 914683.3800000001,
        "IBM": 975000.0,
        "KO": 929326.18,
        "MCD": 945578.66,
        "MMM": 940110.43,
        "MRK": 1003471.0800000001,
        "TRV": 1003508.31,
        "BA": 1276613.95,
        "CRM": 1229926.6,
        "CSCO": 1226199.6,
        "DD": 1264381.1,
        "JNJ": 1141858.01,
        "PG": 1235503.22,
        "VZ": 1284776.25,
        "WBA": 1281936.65
      }
    },
    {
      "day": 25,
      "long_fs": {
        "AAPL": 993976.8,
        "AMGN": 988437.76,
        "AXP": 958097.9999999999,
        "CAT": 1097926.56,
        "GS": 909117.6900000001,
        "IBM": 975929.5,
        "KO": 924386.64,
        "MCD": 936399.6000000001,
        "MMM": 939134.0,
        "MRK": 1003084.8,
        "TRV": 984928.0
      },
      "long_total": 10711429.350000001,
      "short_fs": {
        "BA": 1273920.49,
        "CRM": 1190440.9,
        "CSCO": 1221393.75,
        "DD": 1262232.2000000002,
        "JNJ": 1154966.13,
        "PG": 1243712.24,
        "VZ": 1276986.3699999999,
        "WBA": 1294711.31
      },
      "short_total": 9918363.39,
      "qutrit_total": 10629792.740000002,
      "total_cap": 10629792.740000002,
      "stock_caps": {
        "AAPL": 993976.8,
        "AMGN": 988437.76,
        "AXP": 958097.9999999999,
        "CAT": 1097926.56,
        "GS": 909117.6900000001,
        "IBM": 975929.5,
        "KO": 924386.64,
        "MCD": 936399.6000000001,
        "MMM": 939134.0,
        "MRK": 1003084.8,
        "TRV": 984928.0,
        "BA": 1273920.49,
        "CRM": 1190440.9,
        "CSCO": 1221393.75,
        "DD": 1262232.2000000002,
        "JNJ": 1154966.13,
        "PG": 1243712.24,
        "VZ": 1276986.3699999999,
        "WBA": 1294711.31
      }
    },
    {
      "day": 26,
      "long_fs": {
        "AAPL": 975150.2000000002,
        "AMGN": 987186.6,
        "AXP": 946560.7,
        "CAT": 1074110.68,
        "GS": 897349.4400000001,
        "IBM": 965620.5,
        "KO": 923430.6000000001,
        "MCD": 942771.84,
        "MMM": 935153.17,
        "MRK": 1005788.76,
        "TRV": 982598.69
      },
      "long_total": 10635731.18,
      "short_fs": {
        "BA": 1328623.38,
        "CRM": 1242547.5999999999,
        "CSCO": 1243134.5,
        "DD": 1293308.6,
        "JNJ": 1146278.19,
        "PG": 1239345.74,
        "VZ": 1269474.7000000002,
        "WBA": 1292211.92
      },
      "short_total": 10054924.63,
      "qutrit_total": 10690655.810000002,
      "total_cap": 10690655.810000002,
      "stock_caps": {
        "AAPL": 975150.2000000002,
        "AMGN": 987186.6,
        "AXP": 946560.7,
        "CAT": 1074110.68,
        "GS": 897349.4400000001,
        "IBM": 965620.5,
        "KO": 923430.6000000001,
        "MCD": 942771.84,
        "MMM": 935153.17,
        "MRK": 1005788.76,
        "TRV": 982598.69,
        "BA": 1328623.38,
        "CRM": 1242547.5999999999,
        "CSCO": 1243134.5,
        "DD": 1293308.6,
        "JNJ": 1146278.19,
        "PG": 1239345.74,
        "VZ": 1269474.7000000002,
        "WBA": 1292211.92
      }
    },
    {
      "day": 27,
      "long_fs": {
        "AAPL": 957159.1000000002,
        "AMGN": 1008859.9199999999,
        "AXP": 937933.25,
        "CAT": 1075055.36,
        "GS": 876028.14,
        "IBM": 969338.5,
        "KO": 932672.3200000001,
        "MCD": 953961.1900000001,
        "MMM": 943941.04,
        "MRK": 1020853.68,
        "TRV": 989044.9200000002
      },
      "long_total": 10664857.42,
      "short_fs": {
        "BA": 1353826.47,
        "CRM": 1298320.4,
        "CSCO": 1255721.25,
        "DD": 1339923.2,
        "JNJ": 1111069.1700000002,
        "PG": 1221355.76,
        "VZ": 1259737.35,
        "WBA": 1269439.7
      },
      "short_total": 10109393.299999999,
      "qutrit_total": 10774250.719999999,
      "total_cap": 10774250.719999999,
      "stock_caps": {
        "AAPL": 957159.1000000002,
        "AMGN": 1008859.9199999999,
        "AXP": 937933.25,
        "CAT": 1075055.36,
        "GS": 876028.14,
        "IBM": 969338.5,
        "KO": 932672.3200000001,
        "MCD": 953961.1900000001,
        "MMM": 943941.04,
        "MRK": 1020853.68,
        "TRV": 989044.9200000002,
        "BA": 1353826.47,
        "CRM": 1298320.4,
        "CSCO": 1255721.25,
        "DD": 1339923.2,
        "JNJ": 1111069.1700000002,
        "PG": 1221355.76,
        "VZ": 1259737.35,
        "WBA": 1269439.7
      }
    },
    {
      "day": 28,
      "long_fs": {
        "AAPL": 958885.8,
        "AMGN": 1015761.4799999999,
        "AXP": 931194.6499999999,
        "CAT": 1073514.04,
        "GS": 870185.55,
        "IBM": 963085.5,
        "KO": 937771.2000000001,
        "MCD": 964960.8900000001,
        "MMM": 941762.85,
        "MRK": 1042871.64,
        "TRV": 986390.5900000001
      },
      "long_total": 10686394.19,
      "short_fs": {
        "BA": 1358636.22,
        "CRM": 1302226.9,
        "CSCO": 1249771.15,
        "DD": 1347692.3000000003,
        "JNJ": 1114651.04,
        "PG": 1204763.06,
        "VZ": 1256955.25,
        "WBA": 1247222.9
      },
      "short_total": 10081918.82,
      "qutrit_total": 10768313.009999998,
      "total_cap": 10768313.009999998,
      "stock_caps": {
        "AAPL": 958885.8,
        "AMGN": 1015761.4799999999,
        "AXP": 931194.6499999999,
        "CAT": 1073514.04,
        "GS": 870185.55,
        "IBM": 963085.5,
        "KO": 937771.2000000001,
        "MCD": 964960.8900000001,
        "MMM": 941762.85,
        "MRK": 1042871.64,
        "TRV": 986390.5900000001,
        "BA": 1358636.22,
        "CRM": 1302226.9,
        "CSCO": 1249771.15,
        "DD": 1347692.3000000003,
        "JNJ": 1114651.04,
        "PG": 1204763.06,
        "VZ": 1256955.25,
        "WBA": 1247222.9
      }
    },
    {
      "day": 29,
      "long_fs": {
        "AAPL": 947467.3000000002,
        "AMGN": 1017295.16,
        "AXP": 937882.2,
        "CAT": 1079132.4,
        "GS": 890233.11,
        "IBM": 956917.0,
        "KO": 943507.4400000001,
        "MCD": 953961.1900000001,
        "MMM": 940861.53,
        "MRK": 1053429.96,
        "TRV": 1001395.6800000002
      },
      "long_total": 10722092.969999999,
      "short_fs": {
        "BA": 1376400.23,
        "CRM": 1320136.7,
        "CSCO": 1257780.9,
        "DD": 1362073.4,
        "JNJ": 1111907.48,
        "PG": 1194632.78,
        "VZ": 1236645.9200000002,
        "WBA": 1238613.89
      },
      "short_total": 10098191.3,
      "qutrit_total": 10820284.27,
      "total_cap": 10820284.27,
      "stock_caps": {
        "AAPL": 947467.3000000002,
        "AMGN": 1017295.16,
        "AXP": 937882.2,
        "CAT": 1079132.4,
        "GS": 890233.11,
        "IBM": 956917.0,
        "KO": 943507.4400000001,
        "MCD": 953961.1900000001,
        "MMM": 940861.53,
        "MRK": 1053429.96,
        "TRV": 1001395.6800000002,
        "BA": 1376400.23,
        "CRM": 1320136.7,
        "CSCO": 1257780.9,
        "DD": 1362073.4,
        "JNJ": 1111907.48,
        "PG": 1194632.78,
        "VZ": 1236645.9200000002,
        "WBA": 1238613.89
      }
    },
    {
      "day": 30,
      "long_fs": {
        "AAPL": 923293.5000000001,
        "AMGN": 1012653.76,
        "AXP": 906588.5499999999,
        "CAT": 1074259.84,
        "GS": 888488.64,
        "IBM": 946692.5,
        "KO": 943188.76,
        "MCD": 950130.26,
        "MMM": 942814.39,
        "MRK": 1040811.48,
        "TRV": 1005620.94
      },
      "long_total": 10634552.62,
      "short_fs": {
        "BA": 1377490.44,
        "CRM": 1330413.8,
        "CSCO": 1289819.9,
        "DD": 1368024.2,
        "JNJ": 1129283.3599999999,
        "PG": 1199610.59,
        "VZ": 1228021.41,
        "WBA": 1266107.18
      },
      "short_total": 10188770.879999999,
      "qutrit_total": 10823323.5,
      "total_cap": 10823323.5,
      "stock_caps": {
        "AAPL": 923293.5000000001,
        "AMGN": 1012653.76,
        "AXP": 906588.5499999999,
        "CAT": 1074259.84,
        "GS": 888488.64,
        "IBM": 946692.5,
        "KO": 943188.76,
        "MCD": 950130.26,
        "MMM": 942814.39,
        "MRK": 1040811.48,
        "TRV": 1005620.94,
        "BA": 1377490.44,
        "CRM": 1330413.8,
        "CSCO": 1289819.9,
        "DD": 1368024.2,
        "JNJ": 1129283.3599999999,
        "PG": 1199610.59,
        "VZ": 1228021.41,
        "WBA": 1266107.18
      }
    },
    {
      "day": 31,
      "long_fs": {
        "AAPL": 933932.2000000001,
        "AMGN": 1009303.8799999999,
        "AXP": 896225.3999999999,
        "CAT": 1077491.64,
        "GS": 885775.02,
        "IBM": 943819.5,
        "KO": 954342.56,
        "MCD": 945275.22,
        "MMM": 933125.2000000001,
        "MRK": 1028708.04,
        "TRV": 1001829.04
      },
      "long_total": 10609837.7,
      "short_fs": {
        "BA": 1369474.19,
        "CRM": 1334260.2,
        "CSCO": 1314078.0,
        "DD": 1368354.8000000003,
        "JNJ": 1128826.0999999999,
        "PG": 1203540.44,
        "VZ": 1233585.6099999999,
        "WBA": 1271661.3800000001
      },
      "short_total": 10223780.719999999,
      "qutrit_total": 10833618.419999998,
      "total_cap": 10833618.419999998,
      "stock_caps": {
        "AAPL": 933932.2000000001,
        "AMGN": 1009303.8799999999,
        "AXP": 896225.3999999999,
        "CAT": 1077491.64,
        "GS": 885775.02,
        "IBM": 943819.5,
        "KO": 954342.56,
        "MCD": 945275.22,
        "MMM": 933125.2000000001,
        "MRK": 1028708.04,
        "TRV": 1001829.04,
        "BA": 1369474.19,
        "CRM": 1334260.2,
        "CSCO": 1314078.0,
        "DD": 1368354.8000000003,
        "JNJ": 1128826.0999999999,
        "PG": 1203540.44,
        "VZ": 1233585.6099999999,
        "WBA": 1271661.3800000001
      }
    },
    {
      "day": 32,
      "long_fs": {
        "AAPL": 949194.0000000001,
        "AMGN": 1023308.7999999999,
        "AXP": 916900.65,
        "CAT": 1085297.68,
        "GS": 891839.1300000001,
        "IBM": 945002.5,
        "KO": 956892.0,
        "MCD": 953468.1000000001,
        "MMM": 933650.97,
        "MRK": 1034759.76,
        "TRV": 995166.1300000001
      },
      "long_total": 10685489.72,
      "short_fs": {
        "BA": 1327212.52,
        "CRM": 1328851.2,
        "CSCO": 1306525.95,
        "DD": 1359924.5,
        "JNJ": 1123034.1400000001,
        "PG": 1199872.5799999998,
        "VZ": 1222457.21,
        "WBA": 1261386.1099999999
      },
      "short_total": 10129264.21,
      "qutrit_total": 10814753.93,
      "total_cap": 10814753.93,
      "stock_caps": {
        "AAPL": 949194.0000000001,
        "AMGN": 1023308.7999999999,
        "AXP": 916900.65,
        "CAT": 1085297.68,
        "GS": 891839.1300000001,
        "IBM": 945002.5,
        "KO": 956892.0,
        "MCD": 953468.1000000001,
        "MMM": 933650.97,
        "MRK": 1034759.76,
        "TRV": 995166.1300000001,
        "BA": 1327212.52,
        "CRM": 1328851.2,
        "CSCO": 1306525.95,
        "DD": 1359924.5,
        "JNJ": 1123034.1400000001,
        "PG": 1199872.5799999998,
        "VZ": 1222457.21,
        "WBA": 1261386.1099999999
      }
    },
    {
      "day": 33,
      "long_fs": {
        "AAPL": 920731.3,
        "AMGN": 1025367.16,
        "AXP": 924915.4999999999,
        "CAT": 1132730.56,
        "GS": 890925.36,
        "IBM": 948129.0,
        "KO": 961034.8400000001,
        "MCD": 950357.84,
        "MMM": 925614.2000000001,
        "MRK": 1044159.2400000001,
        "TRV": 998037.1400000001
      },
      "long_total": 10722012.14,
      "short_fs": {
        "BA": 1333176.6099999999,
        "CRM": 1366594.0,
        "CSCO": 1328953.25,
        "DD": 1364387.6,
        "JNJ": 1128826.0999999999,
        "PG": 1207120.97,
        "VZ": 1229690.6700000002,
        "WBA": 1255554.2
      },
      "short_total": 10214303.399999999,
      "qutrit_total": 10936315.54,
      "total_cap": 10936315.54,
      "stock_caps": {
        "AAPL": 920731.3,
        "AMGN": 1025367.16,
        "AXP": 924915.4999999999,
        "CAT": 1132730.56,
        "GS": 890925.36,
        "IBM": 948129.0,
        "KO": 961034.8400000001,
        "MCD": 950357.84,
        "MMM": 925614.2000000001,
        "MRK": 1044159.2400000001,
        "TRV": 998037.1400000001,
        "BA": 1333176.6099999999,
        "CRM": 1366594.0,
        "CSCO": 1328953.25,
        "DD": 1364387.6,
        "JNJ": 1128826.0999999999,
        "PG": 1207120.97,
        "VZ": 1229690.6700000002,
        "WBA": 1255554.2
      }
    },
    {
      "day": 34,
      "long_fs": {
        "AAPL": 919505.9,
        "AMGN": 1016931.9199999999,
        "AXP": 941864.0999999999,
        "CAT": 1143221.48,
        "GS": 913741.92,
        "IBM": 945256.0,
        "KO": 952589.8200000001,
        "MCD": 952443.99,
        "MMM": 918028.0900000001,
        "MRK": 1033987.2,
        "TRV": 1003345.8
      },
      "long_total": 10740926.22,
      "short_fs": {
        "BA": 1346579.78,
        "CRM": 1380957.9,
        "CSCO": 1330326.3499999999,
        "DD": 1366040.6,
        "JNJ": 1145897.1400000001,
        "PG": 1219434.5,
        "VZ": 1239984.44,
        "WBA": 1264163.21
      },
      "short_total": 10293383.919999998,
      "qutrit_total": 11034310.14,
      "total_cap": 11034310.14,
      "stock_caps": {
        "AAPL": 919505.9,
        "AMGN": 1016931.9199999999,
        "AXP": 941864.0999999999,
        "CAT": 1143221.48,
        "GS": 913741.92,
        "IBM": 945256.0,
        "KO": 952589.8200000001,
        "MCD": 952443.99,
        "MMM": 918028.0900000001,
        "MRK": 1033987.2,
        "TRV": 1003345.8,
        "BA": 1346579.78,
        "CRM": 1380957.9,
        "CSCO": 1330326.3499999999,
        "DD": 1366040.6,
        "JNJ": 1145897.1400000001,
        "PG": 1219434.5,
        "VZ": 1239984.44,
        "WBA": 1264163.21
      }
    },
    {
      "day": 35,
      "long_fs": {
        "AAPL": 932484.0000000001,
        "AMGN": 1022743.76,
        "AXP": 955596.5499999999,
        "CAT": 1154358.76,
        "GS": 930549.75,
        "IBM": 967564.0,
        "KO": 961831.54,
        "MCD": 968905.6100000001,
        "MMM": 942664.17,
        "MRK": 1030639.4400000001,
        "TRV": 954267.78
      },
      "long_total": 10821615.36,
      "short_fs": {
        "BA": 1307268.09,
        "CRM": 1354754.3,
        "CSCO": 1313849.15,
        "DD": 1354965.5000000002,
        "JNJ": 1104591.3199999998,
        "PG": 1200309.23,
        "VZ": 1231638.14,
        "WBA": 1233615.1099999999
      },
      "short_total": 10100990.84,
      "qutrit_total": 10922606.2,
      "total_cap": 10922606.2,
      "stock_caps": {
        "AAPL": 932484.0000000001,
        "AMGN": 1022743.76,
        "AXP": 955596.5499999999,
        "CAT": 1154358.76,
        "GS": 930549.75,
        "IBM": 967564.0,
        "KO": 961831.54,
        "MCD": 968905.6100000001,
        "MMM": 942664.17,
        "MRK": 1030639.4400000001,
        "TRV": 954267.78,
        "BA": 1307268.09,
        "CRM": 1354754.3,
        "CSCO": 1313849.15,
        "DD": 1354965.5000000002,
        "JNJ": 1104591.3199999998,
        "PG": 1200309.23,
        "VZ": 1231638.14,
        "WBA": 1233615.1099999999
      }
    },
    {
      "day": 36,
      "long_fs": {
        "AAPL": 931537.1000000001,
        "AMGN": 1030856.1199999999,
        "AXP": 962182.0,
        "CAT": 1168877.0,
        "GS": 944699.3400000001,
        "IBM": 1036262.5,
        "KO": 975056.76,
        "MCD": 970612.46,
        "MMM": 945743.68,
        "MRK": 1038751.3200000001,
        "TRV": 962664.1300000001
      },
      "long_total": 10967252.41,
      "short_fs": {
        "BA": 1322851.68,
        "CRM": 1385585.6,
        "CSCO": 1286615.9999999998,
        "DD": 1333641.8,
        "JNJ": 1098418.31,
        "PG": 1165726.55,
        "VZ": 1216058.3800000001,
        "WBA": 1207510.3699999999
      },
      "short_total": 10016408.69,
      "qutrit_total": 10983661.100000001,
      "total_cap": 10983661.100000001,
      "stock_caps": {
        "AAPL": 931537.1000000001,
        "AMGN": 1030856.1199999999,
        "AXP": 962182.0,
        "CAT": 1168877.0,
        "GS": 944699.3400000001,
        "IBM": 1036262.5,
        "KO": 975056.76,
        "MCD": 970612.46,
        "MMM": 945743.68,
        "MRK": 1038751.3200000001,
        "TRV": 962664.1300000001,
        "BA": 1322851.68,
        "CRM": 1385585.6,
        "CSCO": 1286615.9999999998,
        "DD": 1333641.8,
        "JNJ": 1098418.31,
        "PG": 1165726.55,
        "VZ": 1216058.3800000001,
        "WBA": 1207510.3699999999
      }
    },
    {
      "day": 37,
      "long_fs": {
        "AAPL": 927025.4,
        "AMGN": 1031179.0,
        "AXP": 948296.4,
        "CAT": 1156397.28,
        "GS": 925980.9000000001,
        "IBM": 1047670.0,
        "KO": 978721.5800000001,
        "MCD": 968336.66,
        "MMM": 953179.5700000001,
        "MRK": 1035918.6000000001,
        "TRV": 954809.48
      },
      "long_total": 10927524.870000001,
      "short_fs": {
        "BA": 1339076.5699999998,
        "CRM": 1439435.2000000002,
        "CSCO": 1292108.4,
        "DD": 1348353.5,
        "JNJ": 1102457.44,
        "PG": 1166774.51,
        "VZ": 1201869.6700000002,
        "WBA": 1200012.2
      },
      "short_total": 10090087.489999998,
      "qutrit_total": 11017612.36,
      "total_cap": 11017612.36,
      "stock_caps": {
        "AAPL": 927025.4,
        "AMGN": 1031179.0,
        "AXP": 948296.4,
        "CAT": 1156397.28,
        "GS": 925980.9000000001,
        "IBM": 1047670.0,
        "KO": 978721.5800000001,
        "MCD": 968336.66,
        "MMM": 953179.5700000001,
        "MRK": 1035918.6000000001,
        "TRV": 954809.48,
        "BA": 1339076.5699999998,
        "CRM": 1439435.2000000002,
        "CSCO": 1292108.4,
        "DD": 1348353.5,
        "JNJ": 1102457.44,
        "PG": 1166774.51,
        "VZ": 1201869.6700000002,
        "WBA": 1200012.2
      }
    },
    {
      "day": 38,
      "long_fs": {
        "AAPL": 901236.3,
        "AMGN": 1010555.0399999999,
        "AXP": 921750.3999999999,
        "CAT": 1075502.84,
        "GS": 885747.3300000001,
        "IBM": 1035755.5,
        "KO": 964540.3200000001,
        "MCD": 949068.22,
        "MMM": 936805.5900000001,
        "MRK": 1016218.3200000001,
        "TRV": 937745.9300000002
      },
      "long_total": 10634935.790000001,
      "short_fs": {
        "BA": 1365369.87,
        "CRM": 1474173.0,
        "CSCO": 1324605.0999999999,
        "DD": 1387694.9,
        "JNJ": 1116327.6600000001,
        "PG": 1177952.75,
        "VZ": 1275038.9,
        "WBA": 1235281.3699999999
      },
      "short_total": 10356443.549999999,
      "qutrit_total": 10991379.34,
      "total_cap": 10991379.34,
      "stock_caps": {
        "AAPL": 901236.3,
        "AMGN": 1010555.0399999999,
        "AXP": 921750.3999999999,
        "CAT": 1075502.84,
        "GS": 885747.3300000001,
        "IBM": 1035755.5,
        "KO": 964540.3200000001,
        "MCD": 949068.22,
        "MMM": 936805.5900000001,
        "MRK": 1016218.3200000001,
        "TRV": 937745.9300000002,
        "BA": 1365369.87,
        "CRM": 1474173.0,
        "CSCO": 1324605.0999999999,
        "DD": 1387694.9,
        "JNJ": 1116327.6600000001,
        "PG": 1177952.75,
        "VZ": 1275038.9,
        "WBA": 1235281.3699999999
      }
    },
    {
      "day": 39,
      "long_fs": {
        "AAPL": 907307.6000000001,
        "AMGN": 1017900.5599999999,
        "AXP": 939924.2,
        "CAT": 1077491.64,
        "GS": 890316.1800000002,
        "IBM": 1042093.0,
        "KO": 974738.0800000001,
        "MCD": 959347.25,
        "MMM": 933275.42,
        "MRK": 1026519.12,
        "TRV": 944950.54
      },
      "long_total": 10713873.59,
      "short_fs": {
        "BA": 1371847.0,
        "CRM": 1455361.7,
        "CSCO": 1311331.8,
        "DD": 1379264.6,
        "JNJ": 1082261.79,
        "PG": 1167298.49,
        "VZ": 1313431.8800000001,
        "WBA": 1239447.02
      },
      "short_total": 10320244.28,
      "qutrit_total": 11034117.869999997,
      "total_cap": 11034117.869999997,
      "stock_caps": {
        "AAPL": 907307.6000000001,
        "AMGN": 1017900.5599999999,
        "AXP": 939924.2,
        "CAT": 1077491.64,
        "GS": 890316.1800000002,
        "IBM": 1042093.0,
        "KO": 974738.0800000001,
        "MCD": 959347.25,
        "MMM": 933275.42,
        "MRK": 1026519.12,
        "TRV": 944950.54,
        "BA": 1371847.0,
        "CRM": 1455361.7,
        "CSCO": 1311331.8,
        "DD": 1379264.6,
        "JNJ": 1082261.79,
        "PG": 1167298.49,
        "VZ": 1313431.8800000001,
        "WBA": 1239447.02
      }
    },
    {
      "day": 40,
      "long_fs": {
        "AAPL": 873442.0000000002,
        "AMGN": 1008617.76,
        "AXP": 912101.95,
        "CAT": 1045670.8400000001,
        "GS": 867333.4800000001,
        "IBM": 1020292.0,
        "KO": 961512.8600000001,
        "MCD": 943037.3500000001,
        "MMM": 905785.16,
        "MRK": 1014930.72,
        "TRV": 935308.28
      },
      "long_total": 10488042.4,
      "short_fs": {
        "BA": 1428730.31,
        "CRM": 1482226.4,
        "CSCO": 1335132.2,
        "DD": 1406208.5,
        "JNJ": 1092397.72,
        "PG": 1189916.96,
        "VZ": 1334019.4200000002,
        "WBA": 1253887.94
      },
      "short_total": 10522519.45,
      "qutrit_total": 11010561.850000001,
      "total_cap": 11010561.850000001,
      "stock_caps": {
        "AAPL": 873442.0000000002,
        "AMGN": 1008617.76,
        "AXP": 912101.95,
        "CAT": 1045670.8400000001,
        "GS": 867333.4800000001,
        "IBM": 1020292.0,
        "KO": 961512.8600000001,
        "MCD": 943037.3500000001,
        "MMM": 905785.16,
        "MRK": 1014930.72,
        "TRV": 935308.28,
        "BA": 1428730.31,
        "CRM": 1482226.4,
        "CSCO": 1335132.2,
        "DD": 1406208.5,
        "JNJ": 1092397.72,
        "PG": 1189916.96,
        "VZ": 1334019.4200000002,
        "WBA": 1253887.94
      }
    },
    {
      "day": 41,
      "long_fs": {
        "AAPL": 872160.9,
        "AMGN": 1004258.8799999999,
        "AXP": 906894.85,
        "CAT": 1063868.36,
        "GS": 867638.0700000001,
        "IBM": 1011842.0,
        "KO": 969161.18,
        "MCD": 937575.4299999999,
        "MMM": 905710.05,
        "MRK": 1014158.16,
        "TRV": 940129.4100000001
      },
      "long_total": 10493407.290000001,
      "short_fs": {
        "BA": 1509405.8499999999,
        "CRM": 1454700.6,
        "CSCO": 1371519.3499999999,
        "DD": 1405877.9000000001,
        "JNJ": 1112059.9000000001,
        "PG": 1193410.1600000001,
        "VZ": 1356276.22,
        "WBA": 1271661.3800000001
      },
      "short_total": 10674911.360000001,
      "qutrit_total": 11168318.650000002,
      "total_cap": 11168318.650000002,
      "stock_caps": {
        "AAPL": 872160.9,
        "AMGN": 1004258.8799999999,
        "AXP": 906894.85,
        "CAT": 1063868.36,
        "GS": 867638.0700000001,
        "IBM": 1011842.0,
        "KO": 969161.18,
        "MCD": 937575.4299999999,
        "MMM": 905710.05,
        "MRK": 1014158.16,
        "TRV": 940129.4100000001,
        "BA": 1509405.8499999999,
        "CRM": 1454700.6,
        "CSCO": 1371519.3499999999,
        "DD": 1405877.9000000001,
        "JNJ": 1112059.9000000001,
        "PG": 1193410.1600000001,
        "VZ": 1356276.22,
        "WBA": 1271661.3800000001
      }
    },
    {
      "day": 42,
      "long_fs": {
        "AAPL": 911540.8,
        "AMGN": 961235.1199999999,
        "AXP": 929101.5999999999,
        "CAT": 1056310.92,
        "GS": 881981.4900000001,
        "IBM": 1016912.0,
        "KO": 978402.9,
        "MCD": 964316.0800000001,
        "MMM": 924112.0,
        "MRK": 1064245.8000000003,
        "TRV": 945275.56
      },
      "long_total": 10633444.270000001,
      "short_fs": {
        "BA": 1510944.97,
        "CRM": 1388530.5,
        "CSCO": 1341311.15,
        "DD": 1382901.2000000002,
        "JNJ": 1101695.3399999999,
        "PG": 1160224.76,
        "VZ": 1357945.48,
        "WBA": 1263330.0799999998
      },
      "short_total": 10506883.479999999,
      "qutrit_total": 11140327.75,
      "total_cap": 11140327.75,
      "stock_caps": {
        "AAPL": 911540.8,
        "AMGN": 961235.1199999999,
        "AXP": 929101.5999999999,
        "CAT": 1056310.92,
        "GS": 881981.4900000001,
        "IBM": 1016912.0,
        "KO": 978402.9,
        "MCD": 964316.0800000001,
        "MMM": 924112.0,
        "MRK": 1064245.8000000003,
        "TRV": 945275.56,
        "BA": 1510944.97,
        "CRM": 1388530.5,
        "CSCO": 1341311.15,
        "DD": 1382901.2000000002,
        "JNJ": 1101695.3399999999,
        "PG": 1160224.76,
        "VZ": 1357945.48,
        "WBA": 1263330.0799999998
      }
    },
    {
      "day": 43,
      "long_fs": {
        "AAPL": 878176.5000000001,
        "AMGN": 941297.2799999999,
        "AXP": 891988.25,
        "CAT": 1046864.12,
        "GS": 846206.0100000001,
        "IBM": 990463.5,
        "KO": 954979.92,
        "MCD": 945237.29,
        "MMM": 905785.16,
        "MRK": 1065533.4,
        "TRV": 926641.0800000001
      },
      "long_total": 10393182.51,
      "short_fs": {
        "BA": 1545446.91,
        "CRM": 1447188.1,
        "CSCO": 1379071.4,
        "DD": 1410175.7,
        "JNJ": 1124558.3399999999,
        "PG": 1183629.2,
        "VZ": 1407466.8599999999,
        "WBA": 1322482.31
      },
      "short_total": 10820018.82,
      "qutrit_total": 11213201.329999998,
      "total_cap": 11213201.329999998,
      "stock_caps": {
        "AAPL": 878176.5000000001,
        "AMGN": 941297.2799999999,
        "AXP": 891988.25,
        "CAT": 1046864.12,
        "GS": 846206.0100000001,
        "IBM": 990463.5,
        "KO": 954979.92,
        "MCD": 945237.29,
        "MMM": 905785.16,
        "MRK": 1065533.4,
        "TRV": 926641.0800000001,
        "BA": 1545446.91,
        "CRM": 1447188.1,
        "CSCO": 1379071.4,
        "DD": 1410175.7,
        "JNJ": 1124558.3399999999,
        "PG": 1183629.2,
        "VZ": 1407466.8599999999,
        "WBA": 1322482.31
      }
    },
    {
      "day": 44,
      "long_fs": {
        "AAPL": 879903.2000000002,
        "AMGN": 932135.5599999999,
        "AXP": 876213.7999999999,
        "CAT": 1054471.28,
        "GS": 859857.1800000002,
        "IBM": 996716.5,
        "KO": 937771.2000000001,
        "MCD": 935678.9299999999,
        "MMM": 916375.67,
        "MRK": 1053043.6800000002,
        "TRV": 921386.5900000001
      },
      "long_total": 10363563.59,
      "short_fs": {
        "BA": 1546921.9,
        "CRM": 1437391.8,
        "CSCO": 1358932.5999999999,
        "DD": 1410671.6,
        "JNJ": 1138428.56,
        "PG": 1201444.52,
        "VZ": 1409136.1199999999,
        "WBA": 1319149.7899999998
      },
      "short_total": 10822076.889999999,
      "qutrit_total": 11185640.479999997,
      "total_cap": 11185640.479999997,
      "stock_caps": {
        "AAPL": 879903.2000000002,
        "AMGN": 932135.5599999999,
        "AXP": 876213.7999999999,
        "CAT": 1054471.28,
        "GS": 859857.1800000002,
        "IBM": 996716.5,
        "KO": 937771.2000000001,
        "MCD": 935678.9299999999,
        "MMM": 916375.67,
        "MRK": 1053043.6800000002,
        "TRV": 921386.5900000001,
        "BA": 1546921.9,
        "CRM": 1437391.8,
        "CSCO": 1358932.5999999999,
        "DD": 1410671.6,
        "JNJ": 1138428.56,
        "PG": 1201444.52,
        "VZ": 1409136.1199999999,
        "WBA": 1319149.7899999998
      }
    },
    {
      "day": 45,
      "long_fs": {
        "AAPL": 888369.6000000001,
        "AMGN": 937261.2799999999,
        "AXP": 878715.25,
        "CAT": 1062177.8800000001,
        "GS": 871597.7400000001,
        "IBM": 992829.5,
        "KO": 932353.64,
        "MCD": 932758.3200000001,
        "MMM": 929970.5800000001,
        "MRK": 1046476.9199999999,
        "TRV": 930432.98
      },
      "long_total": 10402953.69,
      "short_fs": {
        "BA": 1515049.29,
        "CRM": 1432704.0,
        "CSCO": 1357559.5,
        "DD": 1402737.2000000002,
        "JNJ": 1141095.9100000001,
        "PG": 1219259.84,
        "VZ": 1386879.32,
        "WBA": 1307485.97
      },
      "short_total": 10762771.030000001,
      "qutrit_total": 11165724.719999999,
      "total_cap": 11165724.719999999,
      "stock_caps": {
        "AAPL": 888369.6000000001,
        "AMGN": 937261.2799999999,
        "AXP": 878715.25,
        "CAT": 1062177.8800000001,
        "GS": 871597.7400000001,
        "IBM": 992829.5,
        "KO": 932353.64,
        "MCD": 932758.3200000001,
        "MMM": 929970.5800000001,
        "MRK": 1046476.9199999999,
        "TRV": 930432.98,
        "BA": 1515049.29,
        "CRM": 1432704.0,
        "CSCO": 1357559.5,
        "DD": 1402737.2000000002,
        "JNJ": 1141095.9100000001,
        "PG": 1219259.84,
        "VZ": 1386879.32,
        "WBA": 1307485.97
      }
    },
    {
      "day": 46,
      "long_fs": {
        "AAPL": 924797.4000000001,
        "AMGN": 953042.0399999999,
        "AXP": 907864.7999999999,
        "CAT": 1106776.72,
        "GS": 897764.7900000002,
        "IBM": 1029333.5,
        "KO": 961194.18,
        "MCD": 964809.17,
        "MMM": 968577.12,
        "MRK": 1063473.2400000002,
        "TRV": 950421.71
      },
      "long_total": 10728064.669999998,
      "short_fs": {
        "BA": 1493309.22,
        "CRM": 1390093.1,
        "CSCO": 1319570.4,
        "DD": 1363065.2,
        "JNJ": 1126539.8,
        "PG": 1209828.2,
        "VZ": 1358501.9,
        "WBA": 1265274.0499999998
      },
      "short_total": 10526181.870000001,
      "qutrit_total": 11254246.54,
      "total_cap": 11254246.54,
      "stock_caps": {
        "AAPL": 924797.4000000001,
        "AMGN": 953042.0399999999,
        "AXP": 907864.7999999999,
        "CAT": 1106776.72,
        "GS": 897764.7900000002,
        "IBM": 1029333.5,
        "KO": 961194.18,
        "MCD": 964809.17,
        "MMM": 968577.12,
        "MRK": 1063473.2400000002,
        "TRV": 950421.71,
        "BA": 1493309.22,
        "CRM": 1390093.1,
        "CSCO": 1319570.4,
        "DD": 1363065.2,
        "JNJ": 1126539.8,
        "PG": 1209828.2,
        "VZ": 1358501.9,
        "WBA": 1265274.0499999998
      }
    },
    {
      "day": 47,
      "long_fs": {
        "AAPL": 873274.9000000001,
        "AMGN": 945979.0399999999,
        "AXP": 873099.7499999999,
        "CAT": 1073663.2,
        "GS": 867195.03,
        "IBM": 1018264.0,
        "KO": 953545.8600000001,
        "MCD": 944326.97,
        "MMM": 938683.3400000001,
        "MRK": 1057292.7600000002,
        "TRV": 931787.23
      },
      "long_total": 10477122.08,
      "short_fs": {
        "BA": 1534993.72,
        "CRM": 1468944.3,
        "CSCO": 1364653.8499999999,
        "DD": 1406704.4000000001,
        "JNJ": 1152756.04,
        "PG": 1233581.96,
        "VZ": 1371021.35,
        "WBA": 1284158.3299999998
      },
      "short_total": 10816813.950000001,
      "qutrit_total": 11293936.030000001,
      "total_cap": 11293936.030000001,
      "stock_caps": {
        "AAPL": 873274.9000000001,
        "AMGN": 945979.0399999999,
        "AXP": 873099.7499999999,
        "CAT": 1073663.2,
        "GS": 867195.03,
        "IBM": 1018264.0,
        "KO": 953545.8600000001,
        "MCD": 944326.97,
        "MMM": 938683.3400000001,
        "MRK": 1057292.7600000002,
        "TRV": 931787.23,
        "BA": 1534993.72,
        "CRM": 1468944.3,
        "CSCO": 1364653.8499999999,
        "DD": 1406704.4000000001,
        "JNJ": 1152756.04,
        "PG": 1233581.96,
        "VZ": 1371021.35,
        "WBA": 1284158.3299999998
      }
    },
    {
      "day": 48,
      "long_fs": {
        "AAPL": 876115.6000000001,
        "AMGN": 954656.44,
        "AXP": 853394.45,
        "CAT": 1067299.04,
        "GS": 866890.4400000001,
        "IBM": 1031361.5,
        "KO": 956892.0,
        "MCD": 951381.9500000001,
        "MMM": 939134.0,
        "MRK": 1061928.12,
        "TRV": 929782.94
      },
      "long_total": 10488846.480000002,
      "short_fs": {
        "BA": 1545062.13,
        "CRM": 1484510.2000000002,
        "CSCO": 1371061.65,
        "DD": 1418606.0,
        "JNJ": 1155728.23,
        "PG": 1220919.11,
        "VZ": 1361005.79,
        "WBA": 1278326.42
      },
      "short_total": 10835219.530000001,
      "qutrit_total": 11324066.010000005,
      "total_cap": 11324066.010000005,
      "stock_caps": {
        "AAPL": 876115.6000000001,
        "AMGN": 954656.44,
        "AXP": 853394.45,
        "CAT": 1067299.04,
        "GS": 866890.4400000001,
        "IBM": 1031361.5,
        "KO": 956892.0,
        "MCD": 951381.9500000001,
        "MMM": 939134.0,
        "MRK": 1061928.12,
        "TRV": 929782.94,
        "BA": 1545062.13,
        "CRM": 1484510.2000000002,
        "CSCO": 1371061.65,
        "DD": 1418606.0,
        "JNJ": 1155728.23,
        "PG": 1220919.11,
        "VZ": 1361005.79,
        "WBA": 1278326.42
      }
    },
    {
      "day": 49,
      "long_fs": {
        "AAPL": 847040.2000000002,
        "AMGN": 965715.08,
        "AXP": 822100.8,
        "CAT": 1025733.12,
        "GS": 855620.61,
        "IBM": 1019362.5,
        "KO": 954979.92,
        "MCD": 938902.9800000001,
        "MMM": 957010.18,
        "MRK": 1052914.92,
        "TRV": 931299.7
      },
      "long_total": 10370690.01,
      "short_fs": {
        "BA": 1645040.8,
        "CRM": 1520990.9,
        "CSCO": 1379529.0999999999,
        "DD": 1436623.7000000002,
        "JNJ": 1148412.0699999998,
        "PG": 1224150.3199999998,
        "VZ": 1352659.49,
        "WBA": 1282214.3599999999
      },
      "short_total": 10989620.74,
      "qutrit_total": 11360310.75,
      "total_cap": 11360310.75,
      "stock_caps": {
        "AAPL": 847040.2000000002,
        "AMGN": 965715.08,
        "AXP": 822100.8,
        "CAT": 1025733.12,
        "GS": 855620.61,
        "IBM": 1019362.5,
        "KO": 954979.92,
        "MCD": 938902.9800000001,
        "MMM": 957010.18,
        "MRK": 1052914.92,
        "TRV": 931299.7,
        "BA": 1645040.8,
        "CRM": 1520990.9,
        "CSCO": 1379529.0999999999,
        "DD": 1436623.7000000002,
        "JNJ": 1148412.0699999998,
        "PG": 1224150.3199999998,
        "VZ": 1352659.49,
        "WBA": 1282214.3599999999
      }
    },
    {
      "day": 50,
      "long_fs": {
        "AAPL": 860686.7000000001,
        "AMGN": 971648.0,
        "AXP": 826235.85,
        "CAT": 1009325.52,
        "GS": 845015.3400000001,
        "IBM": 979140.5,
        "KO": 946216.2200000001,
        "MCD": 932037.65,
        "MMM": 936505.1500000001,
        "MRK": 1054975.08,
        "TRV": 937095.8900000001
      },
      "long_total": 10298891.900000002,
      "short_fs": {
        "BA": 1647349.48,
        "CRM": 1499775.6,
        "CSCO": 1366026.95,
        "DD": 1453319.0,
        "JNJ": 1150241.1099999999,
        "PG": 1230874.73,
        "VZ": 1364066.1,
        "WBA": 1297210.7
      },
      "short_total": 11008863.67,
      "qutrit_total": 11307755.57,
      "total_cap": 11307755.57,
      "stock_caps": {
        "AAPL": 860686.7000000001,
        "AMGN": 971648.0,
        "AXP": 826235.85,
        "CAT": 1009325.52,
        "GS": 845015.3400000001,
        "IBM": 979140.5,
        "KO": 946216.2200000001,
        "MCD": 932037.65,
        "MMM": 936505.1500000001,
        "MRK": 1054975.08,
        "TRV": 937095.8900000001,
        "BA": 1647349.48,
        "CRM": 1499775.6,
        "CSCO": 1366026.95,
        "DD": 1453319.0,
        "JNJ": 1150241.1099999999,
        "PG": 1230874.73,
        "VZ": 1364066.1,
        "WBA": 1297210.7
      }
    },
    {
      "day": 51,
      "long_fs": {
        "AAPL": 816071.0000000001,
        "AMGN": 971365.4799999999,
        "AXP": 813779.6499999999,
        "CAT": 1020363.36,
        "GS": 835296.1500000001,
        "IBM": 991393.0,
        "KO": 950677.74,
        "MCD": 927296.4,
        "MMM": 919530.29,
        "MRK": 1071585.12,
        "TRV": 933791.52
      },
      "long_total": 10251159.71,
      "short_fs": {
        "BA": 1670179.76,
        "CRM": 1534934.1,
        "CSCO": 1386623.45,
        "DD": 1452327.2,
        "JNJ": 1157557.27,
        "PG": 1248777.3800000001,
        "VZ": 1370186.72,
        "WBA": 1296099.8599999999
      },
      "short_total": 11116685.740000002,
      "qutrit_total": 11367845.450000003,
      "total_cap": 11367845.450000003,
      "stock_caps": {
        "AAPL": 816071.0000000001,
        "AMGN": 971365.4799999999,
        "AXP": 813779.6499999999,
        "CAT": 1020363.36,
        "GS": 835296.1500000001,
        "IBM": 991393.0,
        "KO": 950677.74,
        "MCD": 927296.4,
        "MMM": 919530.29,
        "MRK": 1071585.12,
        "TRV": 933791.52,
        "BA": 1670179.76,
        "CRM": 1534934.1,
        "CSCO": 1386623.45,
        "DD": 1452327.2,
        "JNJ": 1157557.27,
        "PG": 1248777.3800000001,
        "VZ": 1370186.72,
        "WBA": 1296099.8599999999
      }
    },
    {
      "day": 52,
      "long_fs": {
        "AAPL": 794125.2000000002,
        "AMGN": 987832.36,
        "AXP": 782537.05,
        "CAT": 1009524.4,
        "GS": 829370.4900000001,
        "IBM": 1007701.5,
        "KO": 953545.8600000001,
        "MCD": 926386.0800000001,
        "MMM": 939509.55,
        "MRK": 1091285.4,
        "TRV": 939154.3500000001
      },
      "long_total": 10260982.24,
      "short_fs": {
        "BA": 1710261.01,
        "CRM": 1540042.5999999999,
        "CSCO": 1394862.05,
        "DD": 1454476.1,
        "JNJ": 1144296.73,
        "PG": 1253842.52,
        "VZ": 1365735.3599999999,
        "WBA": 1301376.35
      },
      "short_total": 11164892.719999999,
      "qutrit_total": 11425874.96,
      "total_cap": 11425874.96,
      "stock_caps": {
        "AAPL": 794125.2000000002,
        "AMGN": 987832.36,
        "AXP": 782537.05,
        "CAT": 1009524.4,
        "GS": 829370.4900000001,
        "IBM": 1007701.5,
        "KO": 953545.8600000001,
        "MCD": 926386.0800000001,
        "MMM": 939509.55,
        "MRK": 1091285.4,
        "TRV": 939154.3500000001,
        "BA": 1710261.01,
        "CRM": 1540042.5999999999,
        "CSCO": 1394862.05,
        "DD": 1454476.1,
        "JNJ": 1144296.73,
        "PG": 1253842.52,
        "VZ": 1365735.3599999999,
        "WBA": 1301376.35
      }
    },
    {
      "day": 53,
      "long_fs": {
        "AAPL": 819468.7000000002,
        "AMGN": 982504.84,
        "AXP": 810512.45,
        "CAT": 1015988.0,
        "GS": 850359.5100000001,
        "IBM": 1013025.0,
        "KO": 971391.9400000001,
        "MCD": 929610.13,
        "MMM": 937631.8,
        "MRK": 1086135.0,
        "TRV": 935958.3200000001
      },
      "long_total": 10352595.690000001,
      "short_fs": {
        "BA": 1684224.23,
        "CRM": 1501218.0,
        "CSCO": 1365798.0999999999,
        "DD": 1439764.4000000001,
        "JNJ": 1152070.1500000001,
        "PG": 1240481.03,
        "VZ": 1362953.26,
        "WBA": 1290545.66
      },
      "short_total": 11037054.830000002,
      "qutrit_total": 11389650.520000003,
      "total_cap": 11389650.520000003,
      "stock_caps": {
        "AAPL": 819468.7000000002,
        "AMGN": 982504.84,
        "AXP": 810512.45,
        "CAT": 1015988.0,
        "GS": 850359.5100000001,
        "IBM": 1013025.0,
        "KO": 971391.9400000001,
        "MCD": 929610.13,
        "MMM": 937631.8,
        "MRK": 1086135.0,
        "TRV": 935958.3200000001,
        "BA": 1684224.23,
        "CRM": 1501218.0,
        "CSCO": 1365798.0999999999,
        "DD": 1439764.4000000001,
        "JNJ": 1152070.1500000001,
        "PG": 1240481.03,
        "VZ": 1362953.26,
        "WBA": 1290545.66
      }
    },
    {
      "day": 54,
      "long_fs": {
        "AAPL": 810723.8,
        "AMGN": 984401.76,
        "AXP": 798668.85,
        "CAT": 1030207.9199999999,
        "GS": 840529.56,
        "IBM": 1023841.0,
        "KO": 975056.76,
        "MCD": 925817.13,
        "MMM": 945217.91,
        "MRK": 1109183.04,
        "TRV": 945275.56
      },
      "long_total": 10388933.290000001,
      "short_fs": {
        "BA": 1704425.18,
        "CRM": 1517925.8,
        "CSCO": 1378613.7,
        "DD": 1439929.7000000002,
        "JNJ": 1142696.3199999998,
        "PG": 1228167.5,
        "VZ": 1342643.93,
        "WBA": 1273883.06
      },
      "short_total": 11028285.19,
      "qutrit_total": 11417218.48,
      "total_cap": 11417218.48,
      "stock_caps": {
        "AAPL": 810723.8,
        "AMGN": 984401.76,
        "AXP": 798668.85,
        "CAT": 1030207.9199999999,
        "GS": 840529.56,
        "IBM": 1023841.0,
        "KO": 975056.76,
        "MCD": 925817.13,
        "MMM": 945217.91,
        "MRK": 1109183.04,
        "TRV": 945275.56,
        "BA": 1704425.18,
        "CRM": 1517925.8,
        "CSCO": 1378613.7,
        "DD": 1439929.7000000002,
        "JNJ": 1142696.3199999998,
        "PG": 1228167.5,
        "VZ": 1342643.93,
        "WBA": 1273883.06
      }
    },
    {
      "day": 55,
      "long_fs": {
        "AAPL": 831332.8000000002,
        "AMGN": 990375.0399999999,
        "AXP": 826337.95,
        "CAT": 1059542.72,
        "GS": 866918.1300000001,
        "IBM": 1049191.0,
        "KO": 972347.9800000001,
        "MCD": 916676.0,
        "MMM": 956709.7400000001,
        "MRK": 1117294.92,
        "TRV": 960930.69
      },
      "long_total": 10547666.969999999,
      "short_fs": {
        "BA": 1653121.18,
        "CRM": 1520209.6,
        "CSCO": 1341997.7,
        "DD": 1402241.3,
        "JNJ": 1137056.78,
        "PG": 1231748.03,
        "VZ": 1345147.82,
        "WBA": 1251943.97
      },
      "short_total": 10883466.38,
      "qutrit_total": 11431133.350000001,
      "total_cap": 11431133.350000001,
      "stock_caps": {
        "AAPL": 831332.8000000002,
        "AMGN": 990375.0399999999,
        "AXP": 826337.95,
        "CAT": 1059542.72,
        "GS": 866918.1300000001,
        "IBM": 1049191.0,
        "KO": 972347.9800000001,
        "MCD": 916676.0,
        "MMM": 956709.7400000001,
        "MRK": 1117294.92,
        "TRV": 960930.69,
        "BA": 1653121.18,
        "CRM": 1520209.6,
        "CSCO": 1341997.7,
        "DD": 1402241.3,
        "JNJ": 1137056.78,
        "PG": 1231748.03,
        "VZ": 1345147.82,
        "WBA": 1251943.97
      }
    },
    {
      "day": 56,
      "long_fs": {
        "AAPL": 784433.4,
        "AMGN": 984765.0,
        "AXP": 796984.2,
        "CAT": 1033936.9199999999,
        "GS": 849639.5700000001,
        "IBM": 1008039.5,
        "KO": 904628.4800000001,
        "MCD": 876546.06,
        "MMM": 935303.39,
        "MRK": 1106479.08,
        "TRV": 944300.5
      },
      "long_total": 10225066.100000001,
      "short_fs": {
        "BA": 1694998.07,
        "CRM": 1558553.4,
        "CSCO": 1393260.0999999999,
        "DD": 1437450.2000000002,
        "JNJ": 1162358.5,
        "PG": 1310781.6800000002,
        "VZ": 1346260.66,
        "WBA": 1356640.64
      },
      "short_total": 11260303.25,
      "qutrit_total": 11485369.350000001,
      "total_cap": 11485369.350000001,
      "stock_caps": {
        "AAPL": 784433.4,
        "AMGN": 984765.0,
        "AXP": 796984.2,
        "CAT": 1033936.9199999999,
        "GS": 849639.5700000001,
        "IBM": 1008039.5,
        "KO": 904628.4800000001,
        "MCD": 876546.06,
        "MMM": 935303.39,
        "MRK": 1106479.08,
        "TRV": 944300.5,
        "BA": 1694998.07,
        "CRM": 1558553.4,
        "CSCO": 1393260.0999999999,
        "DD": 1437450.2000000002,
        "JNJ": 1162358.5,
        "PG": 1310781.6800000002,
        "VZ": 1346260.66,
        "WBA": 1356640.64
      }
    },
    {
      "day": 57,
      "long_fs": {
        "AAPL": 765105.5000000001,
        "AMGN": 988034.16,
        "AXP": 786263.7,
        "CAT": 1028069.96,
        "GS": 853710.0,
        "IBM": 983112.0,
        "KO": 886941.74,
        "MCD": 868770.41,
        "MMM": 922985.35,
        "MRK": 1106350.3199999998,
        "TRV": 917107.1600000001
      },
      "long_total": 10106460.3,
      "short_fs": {
        "BA": 1684609.01,
        "CRM": 1568890.6,
        "CSCO": 1545216.5,
        "DD": 1436789.0000000002,
        "JNJ": 1174247.26,
        "PG": 1338203.3,
        "VZ": 1341252.8800000001,
        "WBA": 1372192.4
      },
      "short_total": 11461400.950000001,
      "qutrit_total": 11567861.25,
      "total_cap": 11567861.25,
      "stock_caps": {
        "AAPL": 765105.5000000001,
        "AMGN": 988034.16,
        "AXP": 786263.7,
        "CAT": 1028069.96,
        "GS": 853710.0,
        "IBM": 983112.0,
        "KO": 886941.74,
        "MCD": 868770.41,
        "MMM": 922985.35,
        "MRK": 1106350.3199999998,
        "TRV": 917107.1600000001,
        "BA": 1684609.01,
        "CRM": 1568890.6,
        "CSCO": 1545216.5,
        "DD": 1436789.0000000002,
        "JNJ": 1174247.26,
        "PG": 1338203.3,
        "VZ": 1341252.8800000001,
        "WBA": 1372192.4
      }
    },
    {
      "day": 58,
      "long_fs": {
        "AAPL": 766442.3000000002,
        "AMGN": 999052.44,
        "AXP": 782383.9,
        "CAT": 983620.2799999999,
        "GS": 849833.4000000001,
        "IBM": 974239.5,
        "KO": 901441.68,
        "MCD": 887394.04,
        "MMM": 903306.53,
        "MRK": 1123861.6800000002,
        "TRV": 911365.1400000001
      },
      "long_total": 10082950.89,
      "short_fs": {
        "BA": 1725908.73,
        "CRM": 1544670.3,
        "CSCO": 1517296.8,
        "DD": 1444558.1,
        "JNJ": 1151079.4200000002,
        "PG": 1337417.3299999998,
        "VZ": 1331237.32,
        "WBA": 1362472.5499999998
      },
      "short_total": 11414640.55,
      "qutrit_total": 11497591.440000001,
      "total_cap": 11497591.440000001,
      "stock_caps": {
        "AAPL": 766442.3000000002,
        "AMGN": 999052.44,
        "AXP": 782383.9,
        "CAT": 983620.2799999999,
        "GS": 849833.4000000001,
        "IBM": 974239.5,
        "KO": 901441.68,
        "MCD": 887394.04,
        "MMM": 903306.53,
        "MRK": 1123861.6800000002,
        "TRV": 911365.1400000001,
        "BA": 1725908.73,
        "CRM": 1544670.3,
        "CSCO": 1517296.8,
        "DD": 1444558.1,
        "JNJ": 1151079.4200000002,
        "PG": 1337417.3299999998,
        "VZ": 1331237.32,
        "WBA": 1362472.5499999998
      }
    },
    {
      "day": 59,
      "long_fs": {
        "AAPL": 797188.7000000002,
        "AMGN": 1005267.8799999999,
        "AXP": 811992.8999999999,
        "CAT": 1015093.04,
        "GS": 876997.2900000002,
        "IBM": 994604.0,
        "KO": 929166.8400000001,
        "MCD": 902907.41,
        "MMM": 906761.5900000001,
        "MRK": 1127209.44,
        "TRV": 932274.76
      },
      "long_total": 10299473.85,
      "short_fs": {
        "BA": 1704296.92,
        "CRM": 1540643.5999999999,
        "CSCO": 1507913.95,
        "DD": 1417779.5,
        "JNJ": 1132331.76,
        "PG": 1310694.35,
        "VZ": 1327898.7999999998,
        "WBA": 1329425.06
      },
      "short_total": 11270983.94,
      "qutrit_total": 11570457.79,
      "total_cap": 11570457.79,
      "stock_caps": {
        "AAPL": 797188.7000000002,
        "AMGN": 1005267.8799999999,
        "AXP": 811992.8999999999,
        "CAT": 1015093.04,
        "GS": 876997.2900000002,
        "IBM": 994604.0,
        "KO": 929166.8400000001,
        "MCD": 902907.41,
        "MMM": 906761.5900000001,
        "MRK": 1127209.44,
        "TRV": 932274.76,
        "BA": 1704296.92,
        "CRM": 1540643.5999999999,
        "CSCO": 1507913.95,
        "DD": 1417779.5,
        "JNJ": 1132331.76,
        "PG": 1310694.35,
        "VZ": 1327898.7999999998,
        "WBA": 1329425.06
      }
    },
    {
      "day": 60,
      "long_fs": {
        "AAPL": 781871.2000000002,
        "AMGN": 1016770.4799999999,
        "AXP": 794584.85,
        "CAT": 1022551.04,
        "GS": 869631.75,
        "IBM": 1014546.0,
        "KO": 946375.56,
        "MCD": 927637.77,
        "MMM": 915324.13,
        "MRK": 1136995.2000000002,
        "TRV": 942079.53
      },
      "long_total": 10368377.51,
      "short_fs": {
        "BA": 1734245.63,
        "CRM": 1560897.2999999998,
        "CSCO": 1498302.25,
        "DD": 1431499.4000000001,
        "JNJ": 1117394.5999999999,
        "PG": 1289560.49,
        "VZ": 1303972.74,
        "WBA": 1331369.03
      },
      "short_total": 11267241.44,
      "qutrit_total": 11635618.95,
      "total_cap": 11635618.95,
      "stock_caps": {
        "AAPL": 781871.2000000002,
        "AMGN": 1016770.4799999999,
        "AXP": 794584.85,
        "CAT": 1022551.04,
        "GS": 869631.75,
        "IBM": 1014546.0,
        "KO": 946375.56,
        "MCD": 927637.77,
        "MMM": 915324.13,
        "MRK": 1136995.2000000002,
        "TRV": 942079.53,
        "BA": 1734245.63,
        "CRM": 1560897.2999999998,
        "CSCO": 1498302.25,
        "DD": 1431499.4000000001,
        "JNJ": 1117394.5999999999,
        "PG": 1289560.49,
        "VZ": 1303972.74,
        "WBA": 1331369.03
      }
    },
    {
      "day": 61,
      "long_fs": {
        "AAPL": 782762.4000000001,
        "AMGN": 1021290.7999999999,
        "AXP": 819497.2499999999,
        "CAT": 1040748.56,
        "GS": 872262.3,
        "IBM": 1019024.5,
        "KO": 947012.92,
        "MCD": 925703.34,
        "MMM": 915624.5700000001,
        "MRK": 1126308.12,
        "TRV": 940346.0900000001
      },
      "long_total": 10410590.850000001,
      "short_fs": {
        "BA": 1717187.05,
        "CRM": 1544670.3,
        "CSCO": 1493038.7,
        "DD": 1418771.3,
        "JNJ": 1130959.98,
        "PG": 1309384.4000000001,
        "VZ": 1290896.8699999999,
        "WBA": 1320816.0499999998
      },
      "short_total": 11225724.649999999,
      "qutrit_total": 11636315.5,
      "total_cap": 11636315.5,
      "stock_caps": {
        "AAPL": 782762.4000000001,
        "AMGN": 1021290.7999999999,
        "AXP": 819497.2499999999,
        "CAT": 1040748.56,
        "GS": 872262.3,
        "IBM": 1019024.5,
        "KO": 947012.92,
        "MCD": 925703.34,
        "MMM": 915624.5700000001,
        "MRK": 1126308.12,
        "TRV": 940346.0900000001,
        "BA": 1717187.05,
        "CRM": 1544670.3,
        "CSCO": 1493038.7,
        "DD": 1418771.3,
        "JNJ": 1130959.98,
        "PG": 1309384.4000000001,
        "VZ": 1290896.8699999999,
        "WBA": 1320816.0499999998
      }
    },
    {
      "day": 62,
      "long_fs": {
        "AAPL": 800920.6000000001,
        "AMGN": 1021452.24,
        "AXP": 844307.5499999999,
        "CAT": 1059045.52,
        "GS": 896435.67,
        "IBM": 1037952.5,
        "KO": 950518.4,
        "MCD": 941178.78,
        "MMM": 923436.01,
        "MRK": 1109054.2799999998,
        "TRV": 947279.8500000001
      },
      "long_total": 10531591.4,
      "short_fs": {
        "BA": 1680825.3399999999,
        "CRM": 1527842.2999999998,
        "CSCO": 1470382.5499999998,
        "DD": 1386372.5,
        "JNJ": 1132179.3399999999,
        "PG": 1298992.1300000001,
        "VZ": 1296739.28,
        "WBA": 1304708.8699999999
      },
      "short_total": 11098042.309999999,
      "qutrit_total": 11629633.71,
      "total_cap": 11629633.71,
      "stock_caps": {
        "AAPL": 800920.6000000001,
        "AMGN": 1021452.24,
        "AXP": 844307.5499999999,
        "CAT": 1059045.52,
        "GS": 896435.67,
        "IBM": 1037952.5,
        "KO": 950518.4,
        "MCD": 941178.78,
        "MMM": 923436.01,
        "MRK": 1109054.2799999998,
        "TRV": 947279.8500000001,
        "BA": 1680825.3399999999,
        "CRM": 1527842.2999999998,
        "CSCO": 1470382.5499999998,
        "DD": 1386372.5,
        "JNJ": 1132179.3399999999,
        "PG": 1298992.1300000001,
        "VZ": 1296739.28,
        "WBA": 1304708.8699999999
      }
    },
    {
      "day": 63,
      "long_fs": {
        "AAPL": 833560.8,
        "AMGN": 1030371.7999999999,
        "AXP": 865901.7,
        "CAT": 1079679.3199999998,
        "GS": 910142.22,
        "IBM": 1056035.5,
        "KO": 956095.3,
        "MCD": 955516.3200000001,
        "MMM": 938983.78,
        "MRK": 1118196.2400000002,
        "TRV": 963314.1700000002
      },
      "long_total": 10707807.15,
      "short_fs": {
        "BA": 1651966.84,
        "CRM": 1512036.0,
        "CSCO": 1455965.0,
        "DD": 1370007.8,
        "JNJ": 1119757.1099999999,
        "PG": 1280652.8299999998,
        "VZ": 1287001.93,
        "WBA": 1286102.2999999998
      },
      "short_total": 10963489.809999999,
      "qutrit_total": 11671296.96,
      "total_cap": 11671296.96,
      "stock_caps": {
        "AAPL": 833560.8,
        "AMGN": 1030371.7999999999,
        "AXP": 865901.7,
        "CAT": 1079679.3199999998,
        "GS": 910142.22,
        "IBM": 1056035.5,
        "KO": 956095.3,
        "MCD": 955516.3200000001,
        "MMM": 938983.78,
        "MRK": 1118196.2400000002,
        "TRV": 963314.1700000002,
        "BA": 1651966.84,
        "CRM": 1512036.0,
        "CSCO": 1455965.0,
        "DD": 1370007.8,
        "JNJ": 1119757.1099999999,
        "PG": 1280652.8299999998,
        "VZ": 1287001.93,
        "WBA": 1286102.2999999998
      }
    },
    {
      "day": 64,
      "long_fs": {
        "AAPL": 829104.8000000002,
        "AMGN": 1036345.08,
        "AXP": 861919.7999999999,
        "CAT": 1073265.44,
        "GS": 905351.8500000001,
        "IBM": 1052740.0,
        "KO": 936815.16,
        "MCD": 956805.9400000001,
        "MMM": 937556.69,
        "MRK": 1105706.52,
        "TRV": 969868.74
      },
      "long_total": 10665490.020000001,
      "short_fs": {
        "BA": 1657289.63,
        "CRM": 1541124.4,
        "CSCO": 1469009.45,
        "DD": 1378438.1,
        "JNJ": 1131645.87,
        "PG": 1287551.9000000001,
        "VZ": 1289505.82,
        "WBA": 1282769.78
      },
      "short_total": 11037334.95,
      "qutrit_total": 11702824.969999999,
      "total_cap": 11702824.969999999,
      "stock_caps": {
        "AAPL": 829104.8000000002,
        "AMGN": 1036345.08,
        "AXP": 861919.7999999999,
        "CAT": 1073265.44,
        "GS": 905351.8500000001,
        "IBM": 1052740.0,
        "KO": 936815.16,
        "MCD": 956805.9400000001,
        "MMM": 937556.69,
        "MRK": 1105706.52,
        "TRV": 969868.74,
        "BA": 1657289.63,
        "CRM": 1541124.4,
        "CSCO": 1469009.45,
        "DD": 1378438.1,
        "JNJ": 1131645.87,
        "PG": 1287551.9000000001,
        "VZ": 1289505.82,
        "WBA": 1282769.78
      }
    }
  ]
}